# pydisasm version 6.3.0
# CPython Python bytecode 3.8 (-1)
#   Disassembled from CPython Python 3.11.9 (tags/v3.11.9:de54cf5, Apr  2 2024, 10:12:12) [MSC v.1938 64 bit (AMD64)]
# Method Name:       <module>
# Filename:          <string>
# Argument count:    0
# Position-only argument count: 0
# Keyword-only arguments: 0
# Number of locals:  0
# Stack size:        10
# Flags:             0x00000040 (NOFREE)
# First Line:        1
# Constants:
#    0: 0
#    1: None
#    2: ('Thread',)
#    3: ('ModuleType',)
#    4: ('abc', 'machinery')
#    5: <Code38 code object I1i at 0x1624c4f4d90, file <string>>, line 21
#    6: 'I1i'
#    7: ('ContextMenu',)
#    8: ('getNameTempFile', 'getDateUpdate', 'MoriaDB', 'get_moria')
#    9: ('logger', 'localize', 'KODI_VERSION', 'set_setting', 'ISESTUARYPALANTIR', 'load_json', 'get_setting', 'CACHE', 'DialogImage', 'WINDOW')
#   10: ('P3Item', 'setInfoTag')
#   11: ('Watched',)
#   12: ('load_cookies',)
#   13: <Code38 code object I1ii1111IIi at 0x1624c5b1850, file <string>>, line 64
#   14: 'I1ii1111IIi'
#   15: <Code38 code object oOo0O00O0ooo at 0x1624c5b2dd0, file <string>>, line 84
#   16: 'oOo0O00O0ooo'
#   17: <Code38 code object IIiI1i at 0x1624c5bc090, file <string>>, line 234
#   18: 'IIiI1i'
#   19: <Code38 code object iii1i1iiIi1 at 0x1624c5bc9d0, file <string>>, line 326
#   20: 'iii1i1iiIi1'
#   21: '__main__'
#   22: 'Palantir 3'
#   23: False
#   24: 19.0
#   25: 30057
#   26: 10000
#   27: 'p3UpdateLock'
#   28: 'true'
#   29: 2
#   30: '?reload='
#   31: '&'
#   32: 1
#   33: '='
#   34: 'debrid_pin'
#   35: 'SendClick(10140,28)'
#   36: 'alldebrid'
#   37: 'Alldebrid_apikey'
#   38: 'realdebrid'
#   39: 'Realdebrid_token'
#   40: 'Realdebrid_refresh_token'
#   41: 'Realdebrid_client_id'
#   42: 'Realdebrid_client_secret'
#   43: 'debridlink'
#   44: 'DebridLink_access_token'
#   45: 'DebridLink_refresh_token'
#   46: ''
#   47: 'trakt_pin'
#   48: ('Trakt',)
#   49: 500
#   50: 'reset_cache'
#   51: 'all'
#   52: 'Cache reiniciada'
#   53: 2000
#   54: 'reset_watched'
#   55: 'special://profile/addon_data/plugin.video.palantir3/watched.db'
#   56: 'Reiniciando la sincronizacion con trakt.tv'
#   57: ('target',)
#   58: True
#   59: 'resumable'
#   60: 'limit'
#   61: 'update'
#   62: 12999
#   63: 'P3Updated'
#   64: 'searchYou'
#   65: ('searchYou',)
#   66: 'infoExtra'
#   67: ('Tmdb',)
#   68: 'clear'
#   69: '_'
#   70: 'E'
#   71: '{"jsonrpc": "2.0", "method": "VideoLibrary.GetTVShowDetails", "params": {"tvshowid": %s, "properties": ["uniqueid"]}, "id": 1}'
#   72: 'result'
#   73: 'tvshowdetails'
#   74: 'uniqueid'
#   75: 'tmdb'
#   76: 'movie'
#   77: 100
#   78: '0'
#   79: ('seconds',)
#   80: '.'
#   81: ('tvshow', 'season', 'episode')
#   82: 'tv'
#   83: 'contextMenu'
#   84: 'plugin://plugin.video.palantir3/?'
#   85: 'addRating'
#   86: 3
#   87: ('forzado',)
#   88: 'findByActor'
#   89: 'Dialog.Close(movieinformation,force)'
#   90: 'listado_content_actor'
#   91: ('action', 'content', 'actorID')
#   92: 'limitItemList'
#   93: 'percentPlayed'
#   94: 0.0
#   95: 'resume:false'
#   96: 'special://home/addons/plugin.video.palantir3/icon.png'
#   97: 'special://home/addons/plugin.video.palantir3/fanart.gif'
#   98: 'skin.estuary'
#   99: 'files'
#  100: 'albums'
#  101: 'select label,action,icon,sql,fanart from menus where menu_id = 10 ORDER by item_id asc'
#  102: ('icon', 'fanart', 'content', 'sql')
# Names:
#    0: Iii1i
#    1: re
#    2: os
#    3: sys
#    4: datetime
#    5: xbmc
#    6: xbmcgui
#    7: xbmcplugin
#    8: xbmcvfs
#    9: Ii
#   10: i1i1i1111I
#   11: OooOoo
#   12: I1Ii1I1
#   13: I1I
#   14: i1
#   15: ooOOO
#   16: oOo0O00
#   17: i1iiIII111
#   18: IiIIii11Ii
#   19: xbmcaddon
#   20: ooo000
#   21: Ooo0Ooo
#   22: iI1iII1I1I1i
#   23: threading
#   24: Thread
#   25: builtins
#   26: base64
#   27: types
#   28: ModuleType
#   29: importlib
#   30: abc
#   31: machinery
#   32: iI111iiIi11i
#   33: __import__
#   34: OoOoo0o
#   35: I1i
#   36: b85decode
#   37: libs.ioOooOO
#   38: ContextMenu
#   39: libs.ioiiI1II1
#   40: getNameTempFile
#   41: getDateUpdate
#   42: MoriaDB
#   43: get_moria
#   44: libs.iooooooOoO0
#   45: logger
#   46: localize
#   47: KODI_VERSION
#   48: set_setting
#   49: ISESTUARYPALANTIR
#   50: load_json
#   51: get_setting
#   52: CACHE
#   53: DialogImage
#   54: WINDOW
#   55: libs.ioI1iII
#   56: P3Item
#   57: setInfoTag
#   58: libs.ioIIiII11
#   59: Watched
#   60: libs.ioiIIIiII
#   61: load_cookies
#   62: OOO00000O
#   63: o0
#   64: I1ii1111IIi
#   65: oOo0O00O0ooo
#   66: IIiI1i
#   67: iii1i1iiIi1
#   68: __name__
#   69: o00o
#   70: Ii1iIII11i
#   71: o0i1i
#   72: O0oO0Ooo
#   73: Oo
#   74: Ii111
#   75: Dialog
#   76: ok
#   77: exit
#   78: Window
#   79: getProperty
#   80: len
#   81: argv
#   82: startswith
#   83: IIiIIiIi11I1
#   84: split
#   85: I11
#   86: oo000O0oOO
#   87: o0OOo0
#   88: executebuiltin
#   89: IIiI1iI111
#   90: i1Iii11ii11
#   91: Trakt
#   92: Oo0O0O
#   93: sleep
#   94: authenticationDevices
#   95: clear
#   96: notification
#   97: NOTIFICATION_INFO
#   98: I11I1iI
#   99: translatePath
#  100: iiiIII
#  101: path
#  102: exists
#  103: remove
#  104: daemon
#  105: start
#  106: int
#  107: clearProperty
#  108: setProperty
#  109: libs.ioiIi11II1
#  110: searchYou
#  111: libs.ioiiiIIIiI
#  112: Tmdb
#  113: clearInfoExtra
#  114: I111iI11i
#  115: strip
#  116: OooOoO0o00
#  117: i1II1
#  118: oo00OOO
#  119: I11I111Ii
#  120: executeJSONRPC
#  121: II1Ii11111
#  122: getProgressMovies
#  123: get
#  124: iiiI
#  125: float
#  126: str
#  127: timedelta
#  128: iI1i1Iiii11i
#  129: getInfoExtra
#  130: replace
#  131: ooOOoO00OO
#  132: show
#  133: O0ooOO0O0O0O
#  134: o00ooo0Oooo
#  135: oOO0
#  136: addRatings
#  137: OOoOo
#  138: tourl
#  139: fromurl
#  140: ooOooo
#  141: limitItemList
#  142: __dict__
#  143: percentPlayed
#  144: playContext
#  145: pop
#  146: markAsUnwatched
#  147: content
#  148: tmdb
#  149: season
#  150: episode
#  151: getSkinDir

  3:           0 LOAD_CONST           (0)
               2 LOAD_CONST           (None)
               4 IMPORT_NAME          (re)
               6 STORE_NAME           (re)

  4:           8 LOAD_CONST           (0)
              10 LOAD_CONST           (None)
              12 IMPORT_NAME          (os)
              14 STORE_NAME           (os)

  5:          16 LOAD_CONST           (0)
              18 LOAD_CONST           (None)
              20 IMPORT_NAME          (sys)
              22 STORE_NAME           (sys)

  6:          24 LOAD_CONST           (0)
              26 LOAD_CONST           (None)
              28 IMPORT_NAME          (datetime)
              30 STORE_NAME           (datetime)

  7:          32 LOAD_CONST           (0)
              34 LOAD_CONST           (None)
              36 IMPORT_NAME          (xbmc)
              38 STORE_NAME           (xbmc)

  8:          40 LOAD_CONST           (0)
              42 LOAD_CONST           (None)
              44 IMPORT_NAME          (xbmcgui)
              46 STORE_NAME           (xbmcgui)

  9:          48 LOAD_CONST           (0)
              50 LOAD_CONST           (None)
              52 IMPORT_NAME          (xbmcplugin)
              54 STORE_NAME           (xbmcplugin)

 10:          56 LOAD_CONST           (0)
              58 LOAD_CONST           (None)
              60 IMPORT_NAME          (xbmcvfs)
              62 STORE_NAME           (xbmcvfs)

 13:          64 LOAD_CONST           (0)
              66 LOAD_CONST           (None)
              68 IMPORT_NAME          (xbmcaddon)
              70 STORE_NAME           (xbmcaddon)

 15:          72 LOAD_CONST           (0)
              74 LOAD_CONST           (('Thread',))
              76 IMPORT_NAME          (threading)
              78 IMPORT_FROM          (Thread)
              80 STORE_NAME           (Thread)
              82 POP_TOP

 16:          84 LOAD_CONST           (0)
              86 LOAD_CONST           (None)
              88 IMPORT_NAME          (builtins)
              90 STORE_NAME           (builtins)
              92 LOAD_CONST           (0)
              94 LOAD_CONST           (None)
              96 IMPORT_NAME          (base64)
              98 STORE_NAME           (base64)

 17:         100 LOAD_CONST           (0)
             102 LOAD_CONST           (('ModuleType',))
             104 IMPORT_NAME          (types)
             106 IMPORT_FROM          (ModuleType)
             108 STORE_NAME           (ModuleType)
             110 POP_TOP

 18:         112 LOAD_CONST           (0)
             114 LOAD_CONST           (('abc', 'machinery'))
             116 IMPORT_NAME          (importlib)
             118 IMPORT_FROM          (abc)
             120 STORE_NAME           (abc)
             122 IMPORT_FROM          (machinery)
             124 STORE_NAME           (machinery)
             126 POP_TOP

 19:         128 LOAD_NAME            (base64)
             130 STORE_NAME           (iI111iiIi11i)

 20:         132 LOAD_NAME            (__import__)
             134 STORE_NAME           (OoOoo0o)

 21:         136 LOAD_CONST           (None)
             138 LOAD_CONST           (None)
             140 BUILD_LIST           0
             142 LOAD_CONST           (0)
             144 BUILD_TUPLE          4
             146 LOAD_CONST           (<Code38 code object I1i at 0x1624c4f4d90, file <string>>, line 21)
             148 LOAD_CONST           ("I1i")
             150 MAKE_FUNCTION        (default)
             152 STORE_NAME           (I1i)

 54:         154 LOAD_NAME            (iI111iiIi11i)
             156 LOAD_ATTR            (b85decode)
             158 STORE_NAME           (iI111iiIi11i)

 55:         160 LOAD_NAME            (I1i)
             162 LOAD_NAME            (builtins)
             164 STORE_ATTR           (__import__)

 56:         166 LOAD_CONST           (0)
             168 LOAD_CONST           (('ContextMenu',))
             170 IMPORT_NAME          (libs.ioOooOO)
             172 IMPORT_FROM          (ContextMenu)
             174 STORE_NAME           (ContextMenu)
             176 POP_TOP

 57:         178 LOAD_CONST           (0)
             180 LOAD_CONST           (('getNameTempFile', 'getDateUpdate', 'MoriaDB', 'get_moria'))
             182 IMPORT_NAME          (libs.ioiiI1II1)
             184 IMPORT_FROM          (getNameTempFile)
             186 STORE_NAME           (getNameTempFile)
             188 IMPORT_FROM          (getDateUpdate)
             190 STORE_NAME           (getDateUpdate)
             192 IMPORT_FROM          (MoriaDB)
             194 STORE_NAME           (MoriaDB)
             196 IMPORT_FROM          (get_moria)
             198 STORE_NAME           (get_moria)
             200 POP_TOP

 58:         202 LOAD_CONST           (0)
             204 LOAD_CONST           (('logger', 'localize', 'KODI_VERSION', 'set_setting', 'ISESTUARYPALANTIR', 'load_json', 'get_setting', 'CACHE', 'DialogImage', 'WINDOW'))
             206 IMPORT_NAME          (libs.iooooooOoO0)
             208 IMPORT_FROM          (logger)
             210 STORE_NAME           (logger)
             212 IMPORT_FROM          (localize)
             214 STORE_NAME           (localize)
             216 IMPORT_FROM          (KODI_VERSION)
             218 STORE_NAME           (KODI_VERSION)
             220 IMPORT_FROM          (set_setting)
             222 STORE_NAME           (set_setting)
             224 IMPORT_FROM          (ISESTUARYPALANTIR)
             226 STORE_NAME           (ISESTUARYPALANTIR)
             228 IMPORT_FROM          (load_json)
             230 STORE_NAME           (load_json)
             232 IMPORT_FROM          (get_setting)
             234 STORE_NAME           (get_setting)
             236 IMPORT_FROM          (CACHE)
             238 STORE_NAME           (CACHE)
             240 IMPORT_FROM          (DialogImage)
             242 STORE_NAME           (DialogImage)
             244 IMPORT_FROM          (WINDOW)
             246 STORE_NAME           (WINDOW)
             248 POP_TOP

 59:         250 LOAD_CONST           (0)
             252 LOAD_CONST           (('P3Item', 'setInfoTag'))
             254 IMPORT_NAME          (libs.ioI1iII)
             256 IMPORT_FROM          (P3Item)
             258 STORE_NAME           (P3Item)
             260 IMPORT_FROM          (setInfoTag)
             262 STORE_NAME           (setInfoTag)
             264 POP_TOP

 60:         266 LOAD_CONST           (0)
             268 LOAD_CONST           (('Watched',))
             270 IMPORT_NAME          (libs.ioIIiII11)
             272 IMPORT_FROM          (Watched)
             274 STORE_NAME           (Watched)
             276 POP_TOP

 61:         278 LOAD_CONST           (0)
             280 LOAD_CONST           (('load_cookies',))
             282 IMPORT_NAME          (libs.ioiIIIiII)
             284 IMPORT_FROM          (load_cookies)
             286 STORE_NAME           (load_cookies)
             288 POP_TOP

 62:         290 LOAD_NAME            (load_cookies)
             292 CALL_FUNCTION        (0 positional arguments)
             294 POP_TOP

 64:         296 LOAD_CONST           (<Code38 code object I1ii1111IIi at 0x1624c5b1850, file <string>>, line 64)
             298 LOAD_CONST           ("I1ii1111IIi")
             300 MAKE_FUNCTION        (No arguments)
             302 STORE_NAME           (I1ii1111IIi)

 84:         304 LOAD_CONST           (<Code38 code object oOo0O00O0ooo at 0x1624c5b2dd0, file <string>>, line 84)
             306 LOAD_CONST           ("oOo0O00O0ooo")
             308 MAKE_FUNCTION        (No arguments)
             310 STORE_NAME           (oOo0O00O0ooo)

234:         312 LOAD_CONST           (<Code38 code object IIiI1i at 0x1624c5bc090, file <string>>, line 234)
             314 LOAD_CONST           ("IIiI1i")
             316 MAKE_FUNCTION        (No arguments)
             318 STORE_NAME           (IIiI1i)

326:         320 LOAD_CONST           (<Code38 code object iii1i1iiIi1 at 0x1624c5bc9d0, file <string>>, line 326)
             322 LOAD_CONST           ("iii1i1iiIi1")
             324 MAKE_FUNCTION        (No arguments)
             326 STORE_NAME           (iii1i1iiIi1)

331:         328 LOAD_NAME            (__name__)
             330 LOAD_CONST           ("__main__")
             332 COMPARE_OP           (==)
             334 EXTENDED_ARG         (2048)
             336 POP_JUMP_IF_FALSE    (to 2050)

332:         338 LOAD_CONST           ("Palantir 3")
             340 STORE_NAME           (o00o)

333:         342 LOAD_CONST           (False)
             344 STORE_NAME           (Ii1iIII11i)

335:         346 LOAD_CONST           (None)
             348 STORE_NAME           (O0oO0Ooo)

338:         350 LOAD_NAME            (KODI_VERSION)
             352 LOAD_CONST           (19.0)
             354 COMPARE_OP           (<)
             356 EXTENDED_ARG         (256)
             358 POP_JUMP_IF_FALSE    (to 388)

339:         360 LOAD_NAME            (xbmcgui)
             362 LOAD_METHOD          (Dialog)
             364 CALL_METHOD          (0 positional arguments)
             366 LOAD_METHOD          (ok)
             368 LOAD_NAME            (o00o)
             370 LOAD_NAME            (localize)
             372 LOAD_CONST           (30057)
             374 CALL_FUNCTION        (1 positional argument)
             376 CALL_METHOD          (2 positional arguments)
             378 POP_TOP

340:         380 LOAD_NAME            (exit)
             382 LOAD_CONST           (0)
             384 CALL_FUNCTION        (1 positional argument)
             386 POP_TOP

342:     >>  388 LOAD_NAME            (xbmcgui)
             390 LOAD_METHOD          (Window)
             392 LOAD_CONST           (10000)
             394 CALL_METHOD          (1 positional argument)
             396 LOAD_METHOD          (getProperty)
             398 LOAD_CONST           ("p3UpdateLock")
             400 CALL_METHOD          (1 positional argument)
             402 LOAD_CONST           ("true")
             404 COMPARE_OP           (==)
             406 EXTENDED_ARG         (256)
             408 POP_JUMP_IF_FALSE    (to 418)

343:         410 LOAD_NAME            (exit)
             412 LOAD_CONST           (0)
             414 CALL_FUNCTION        (1 positional argument)
             416 POP_TOP

345:     >>  418 LOAD_NAME            (len)
             420 LOAD_NAME            (sys)
             422 LOAD_ATTR            (argv)
             424 CALL_FUNCTION        (1 positional argument)
             426 LOAD_CONST           (2)
             428 COMPARE_OP           (>)
             430 EXTENDED_ARG         (1792)
             432 POP_JUMP_IF_FALSE    (to 1930)
             434 LOAD_NAME            (sys)
             436 LOAD_ATTR            (argv)
             438 LOAD_CONST           (2)
             440 BINARY_SUBSCR
             442 EXTENDED_ARG         (1792)
             444 POP_JUMP_IF_FALSE    (to 1930)
             446 LOAD_NAME            (sys)
             448 LOAD_ATTR            (argv)
             450 LOAD_CONST           (2)
             452 BINARY_SUBSCR
             454 LOAD_METHOD          (startswith)
             456 LOAD_CONST           ("?reload=")
             458 CALL_METHOD          (1 positional argument)
             460 EXTENDED_ARG         (1792)
             462 POP_JUMP_IF_TRUE     (to 1930)

347:         464 LOAD_CONST           ("&")
             466 LOAD_NAME            (sys)
             468 LOAD_ATTR            (argv)
             470 LOAD_CONST           (2)
             472 BINARY_SUBSCR
             474 COMPARE_OP           (in)
             476 EXTENDED_ARG         (1536)
             478 POP_JUMP_IF_FALSE    (to 1724)

349:         480 LOAD_NAME            (sys)
             482 LOAD_ATTR            (argv)
             484 LOAD_CONST           (2)
             486 BINARY_SUBSCR
             488 LOAD_METHOD          (split)
             490 LOAD_CONST           ("&")
             492 CALL_METHOD          (1 positional argument)
             494 LOAD_CONST           (1)
             496 LOAD_CONST           (None)
             498 BUILD_SLICE          2
             500 BINARY_SUBSCR
             502 GET_ITER
         >>  504 EXTENDED_ARG         (1024)
             506 FOR_ITER             (to 1698)
             508 STORE_NAME           (I11)

350:         510 LOAD_NAME            (I11)
             512 LOAD_METHOD          (split)
             514 LOAD_CONST           ("=")
             516 CALL_METHOD          (1 positional argument)
             518 UNPACK_SEQUENCE      2
             520 STORE_NAME           (oo000O0oOO)
             522 STORE_NAME           (o0OOo0)

352:         524 LOAD_NAME            (oo000O0oOO)
             526 LOAD_CONST           ("debrid_pin")
             528 COMPARE_OP           (==)
             530 EXTENDED_ARG         (512)
             532 POP_JUMP_IF_FALSE    (to 638)

353:         534 LOAD_NAME            (xbmc)
             536 LOAD_METHOD          (executebuiltin)
             538 LOAD_CONST           ("SendClick(10140,28)")
             540 CALL_METHOD          (1 positional argument)
             542 POP_TOP

354:         544 LOAD_NAME            (o0OOo0)
             546 LOAD_CONST           ("alldebrid")
             548 COMPARE_OP           (==)
             550 EXTENDED_ARG         (512)
             552 POP_JUMP_IF_FALSE    (to 562)

355:         554 LOAD_CONST           ("Alldebrid_apikey")
             556 BUILD_LIST           1
             558 STORE_NAME           (IIiI1iI111)
             560 JUMP_FORWARD         (to 604)

356:     >>  562 LOAD_NAME            (o0OOo0)
             564 LOAD_CONST           ("realdebrid")
             566 COMPARE_OP           (==)
             568 EXTENDED_ARG         (512)
             570 POP_JUMP_IF_FALSE    (to 586)

357:         572 LOAD_CONST           ("Realdebrid_token")
             574 LOAD_CONST           ("Realdebrid_refresh_token")
             576 LOAD_CONST           ("Realdebrid_client_id")
             578 LOAD_CONST           ("Realdebrid_client_secret")
             580 BUILD_LIST           4
             582 STORE_NAME           (IIiI1iI111)
             584 JUMP_FORWARD         (to 604)

358:     >>  586 LOAD_NAME            (o0OOo0)
             588 LOAD_CONST           ("debridlink")
             590 COMPARE_OP           (==)
             592 EXTENDED_ARG         (512)
             594 POP_JUMP_IF_FALSE    (to 604)

359:         596 LOAD_CONST           ("DebridLink_access_token")
             598 LOAD_CONST           ("DebridLink_refresh_token")
             600 BUILD_LIST           2
             602 STORE_NAME           (IIiI1iI111)

361:     >>  604 LOAD_NAME            (IIiI1iI111)
             606 GET_ITER
         >>  608 FOR_ITER             (to 626)
             610 STORE_NAME           (i1Iii11ii11)

362:         612 LOAD_NAME            (set_setting)
             614 LOAD_NAME            (i1Iii11ii11)
             616 LOAD_CONST           ("")
             618 CALL_FUNCTION        (2 positional arguments)
             620 POP_TOP

363:         622 EXTENDED_ARG         (512)
             624 JUMP_ABSOLUTE        (to 608)

364:     >>  626 LOAD_NAME            (exit)
             628 LOAD_CONST           (0)
             630 CALL_FUNCTION        (1 positional argument)
             632 POP_TOP

365:         634 EXTENDED_ARG         (256)
             636 JUMP_FORWARD         (to 924)

366:     >>  638 LOAD_NAME            (oo000O0oOO)
             640 LOAD_CONST           ("trakt_pin")
             642 COMPARE_OP           (==)
             644 EXTENDED_ARG         (512)
             646 POP_JUMP_IF_FALSE    (to 704)

367:         648 LOAD_NAME            (xbmc)
             650 LOAD_METHOD          (executebuiltin)
             652 LOAD_CONST           ("SendClick(10140,28)")
             654 CALL_METHOD          (1 positional argument)
             656 POP_TOP

368:         658 LOAD_CONST           (0)
             660 LOAD_CONST           (('Trakt',))
             662 IMPORT_NAME          (libs.ioIIiII11)
             664 IMPORT_FROM          (Trakt)
             666 STORE_NAME           (Trakt)
             668 POP_TOP

370:         670 LOAD_NAME            (Trakt)
             672 CALL_FUNCTION        (0 positional arguments)
             674 STORE_NAME           (Oo0O0O)

371:         676 LOAD_NAME            (xbmc)
             678 LOAD_METHOD          (sleep)
             680 LOAD_CONST           (500)
             682 CALL_METHOD          (1 positional argument)
             684 POP_TOP

372:         686 LOAD_NAME            (Oo0O0O)
             688 LOAD_METHOD          (authenticationDevices)
             690 CALL_METHOD          (0 positional arguments)
             692 POP_TOP

373:         694 LOAD_NAME            (exit)
             696 LOAD_CONST           (0)
             698 CALL_FUNCTION        (1 positional argument)
             700 POP_TOP

374:         702 JUMP_FORWARD         (to 924)

375:     >>  704 LOAD_NAME            (oo000O0oOO)
             706 LOAD_CONST           ("reset_cache")
             708 COMPARE_OP           (==)
             710 EXTENDED_ARG         (512)
             712 POP_JUMP_IF_FALSE    (to 756)

376:         714 LOAD_NAME            (CACHE)
             716 LOAD_METHOD          (clear)
             718 LOAD_CONST           ("all")
             720 CALL_METHOD          (1 positional argument)
             722 POP_TOP

377:         724 LOAD_NAME            (xbmcgui)
             726 LOAD_METHOD          (Dialog)
             728 CALL_METHOD          (0 positional arguments)
             730 LOAD_METHOD          (notification)
             732 LOAD_NAME            (o00o)
             734 LOAD_CONST           ("Cache reiniciada")
             736 LOAD_NAME            (xbmcgui)
             738 LOAD_ATTR            (NOTIFICATION_INFO)
             740 LOAD_CONST           (2000)
             742 CALL_METHOD          (4 positional arguments)
             744 POP_TOP

378:         746 LOAD_NAME            (exit)
             748 LOAD_CONST           (0)
             750 CALL_FUNCTION        (1 positional argument)
             752 POP_TOP

379:         754 JUMP_FORWARD         (to 924)

380:     >>  756 LOAD_NAME            (oo000O0oOO)
             758 LOAD_CONST           ("reset_watched")
             760 COMPARE_OP           (==)
             762 EXTENDED_ARG         (768)
             764 POP_JUMP_IF_FALSE    (to 924)

381:         766 SETUP_FINALLY        (to 798)

382:         768 LOAD_NAME            (Watched)
             770 CALL_FUNCTION        (0 positional arguments)
             772 SETUP_WITH           (to 788)
             774 STORE_NAME           (I11I1iI)

383:         776 LOAD_NAME            (I11I1iI)
             778 LOAD_METHOD          (clear)
             780 CALL_METHOD          (0 positional arguments)
             782 POP_TOP
             784 POP_BLOCK
             786 BEGIN_FINALLY
         >>  788 WITH_CLEANUP_START
             790 WITH_CLEANUP_FINISH
             792 END_FINALLY
             794 POP_BLOCK
             796 JUMP_FORWARD         (to 870)

384:     >>  798 POP_TOP
             800 POP_TOP
             802 POP_TOP

385:         804 SETUP_FINALLY        (to 844)

386:         806 LOAD_NAME            (xbmcvfs)
             808 LOAD_METHOD          (translatePath)

387:         810 LOAD_CONST           ("special://profile/addon_data/plugin.video.palantir3/watched.db")

386:         812 CALL_METHOD          (1 positional argument)
             814 STORE_NAME           (iiiIII)

388:         816 LOAD_NAME            (os)
             818 LOAD_ATTR            (path)
             820 LOAD_METHOD          (exists)
             822 LOAD_NAME            (iiiIII)
             824 CALL_METHOD          (1 positional argument)
             826 EXTENDED_ARG         (768)
             828 POP_JUMP_IF_FALSE    (to 840)

389:         830 LOAD_NAME            (os)
             832 LOAD_METHOD          (remove)
             834 LOAD_NAME            (iiiIII)
             836 CALL_METHOD          (1 positional argument)
             838 POP_TOP
         >>  840 POP_BLOCK
             842 JUMP_FORWARD         (to 864)

390:     >>  844 POP_TOP
             846 POP_TOP
             848 POP_TOP

391:         850 LOAD_NAME            (exit)
             852 LOAD_CONST           (0)
             854 CALL_FUNCTION        (1 positional argument)
             856 POP_TOP

392:         858 POP_EXCEPT
             860 JUMP_FORWARD         (to 864)
             862 END_FINALLY
         >>  864 POP_EXCEPT
             866 JUMP_FORWARD         (to 870)
             868 END_FINALLY

393:     >>  870 LOAD_NAME            (xbmcgui)
             872 LOAD_METHOD          (Dialog)
             874 CALL_METHOD          (0 positional arguments)
             876 LOAD_METHOD          (notification)
             878 LOAD_NAME            (o00o)
             880 LOAD_CONST           ("Reiniciando la sincronizacion con trakt.tv")

394:         882 LOAD_NAME            (xbmcgui)
             884 LOAD_ATTR            (NOTIFICATION_INFO)

394:         886 LOAD_CONST           (2000)

393:         888 CALL_METHOD          (4 positional arguments)
             890 POP_TOP

396:         892 LOAD_NAME            (Thread)
             894 LOAD_NAME            (iii1i1iiIi1)
             896 LOAD_CONST           (('target',))
             898 CALL_FUNCTION_KW     (1 total positional and keyword args)
             900 STORE_NAME           (Oo0O0O)

397:         902 LOAD_CONST           (True)
             904 LOAD_NAME            (Oo0O0O)
             906 STORE_ATTR           (daemon)

398:         908 LOAD_NAME            (Oo0O0O)
             910 LOAD_METHOD          (start)
             912 CALL_METHOD          (0 positional arguments)
             914 POP_TOP

400:         916 LOAD_NAME            (exit)
             918 LOAD_CONST           (0)
             920 CALL_FUNCTION        (1 positional argument)
             922 POP_TOP

402:     >>  924 LOAD_NAME            (ISESTUARYPALANTIR)
             926 EXTENDED_ARG         (256)
             928 POP_JUMP_IF_FALSE    (to 504)

406:         930 LOAD_NAME            (oo000O0oOO)
             932 LOAD_CONST           ("resumable")
             934 COMPARE_OP           (==)
             936 EXTENDED_ARG         (768)
             938 POP_JUMP_IF_FALSE    (to 958)
             940 LOAD_NAME            (o0OOo0)
             942 LOAD_CONST           ("true")
             944 COMPARE_OP           (==)
             946 EXTENDED_ARG         (768)
             948 POP_JUMP_IF_FALSE    (to 958)

407:         950 LOAD_CONST           (True)
             952 STORE_NAME           (Ii1iIII11i)

408:         954 EXTENDED_ARG         (256)
             956 JUMP_ABSOLUTE        (to 504)

409:     >>  958 LOAD_NAME            (oo000O0oOO)
             960 LOAD_CONST           ("limit")
             962 COMPARE_OP           (==)
             964 EXTENDED_ARG         (768)
             966 POP_JUMP_IF_FALSE    (to 998)

410:         968 SETUP_FINALLY        (to 982)

411:         970 LOAD_NAME            (int)
             972 LOAD_NAME            (o0OOo0)
             974 CALL_FUNCTION        (1 positional argument)
             976 STORE_NAME           (O0oO0Ooo)
             978 POP_BLOCK
             980 JUMP_FORWARD         (to 994)

412:     >>  982 POP_TOP
             984 POP_TOP
             986 POP_TOP

412:         988 POP_EXCEPT
             990 JUMP_FORWARD         (to 994)
             992 END_FINALLY

413:     >>  994 EXTENDED_ARG         (256)
             996 JUMP_ABSOLUTE        (to 504)

414:     >>  998 LOAD_NAME            (oo000O0oOO)
            1000 LOAD_CONST           ("update")
            1002 COMPARE_OP           (==)
            1004 EXTENDED_ARG         (1024)
            1006 POP_JUMP_IF_FALSE    (to 1096)

415:        1008 LOAD_NAME            (WINDOW)
            1010 LOAD_METHOD          (getProperty)
            1012 LOAD_CONST           ("p3UpdateLock")
            1014 CALL_METHOD          (1 positional argument)
            1016 LOAD_CONST           ("true")
            1018 COMPARE_OP           (!=)
            1020 EXTENDED_ARG         (1024)
            1022 POP_JUMP_IF_FALSE    (to 1084)

416:        1024 SETUP_FINALLY        (to 1072)

417:        1026 LOAD_NAME            (WINDOW)
            1028 LOAD_METHOD          (setProperty)
            1030 LOAD_CONST           ("p3UpdateLock")
            1032 LOAD_CONST           ("true")
            1034 CALL_METHOD          (2 positional arguments)
            1036 POP_TOP

418:        1038 LOAD_NAME            (oOo0O00O0ooo)
            1040 CALL_FUNCTION        (0 positional arguments)
            1042 POP_TOP

419:        1044 LOAD_NAME            (iii1i1iiIi1)
            1046 CALL_FUNCTION        (0 positional arguments)
            1048 POP_TOP

420:        1050 LOAD_NAME            (xbmcgui)
            1052 LOAD_METHOD          (Window)
            1054 LOAD_CONST           (12999)
            1056 CALL_METHOD          (1 positional argument)
            1058 LOAD_METHOD          (setProperty)
            1060 LOAD_CONST           ("P3Updated")
            1062 LOAD_CONST           ("true")
            1064 CALL_METHOD          (2 positional arguments)
            1066 POP_TOP
            1068 POP_BLOCK
            1070 BEGIN_FINALLY

422:     >> 1072 LOAD_NAME            (WINDOW)
            1074 LOAD_METHOD          (clearProperty)
            1076 LOAD_CONST           ("p3UpdateLock")
            1078 CALL_METHOD          (1 positional argument)
            1080 POP_TOP
            1082 END_FINALLY

423:     >> 1084 LOAD_NAME            (exit)
            1086 LOAD_CONST           (0)
            1088 CALL_FUNCTION        (1 positional argument)
            1090 POP_TOP

424:        1092 EXTENDED_ARG         (256)
            1094 JUMP_ABSOLUTE        (to 504)

425:     >> 1096 LOAD_NAME            (oo000O0oOO)
            1098 LOAD_CONST           ("searchYou")
            1100 COMPARE_OP           (==)
            1102 EXTENDED_ARG         (1024)
            1104 POP_JUMP_IF_FALSE    (to 1136)

426:        1106 LOAD_CONST           (0)
            1108 LOAD_CONST           (('searchYou',))
            1110 IMPORT_NAME          (libs.ioiIi11II1)
            1112 IMPORT_FROM          (searchYou)
            1114 STORE_NAME           (searchYou)
            1116 POP_TOP

427:        1118 LOAD_NAME            (searchYou)
            1120 CALL_FUNCTION        (0 positional arguments)
            1122 POP_TOP

428:        1124 LOAD_NAME            (exit)
            1126 LOAD_CONST           (0)
            1128 CALL_FUNCTION        (1 positional argument)
            1130 POP_TOP

429:        1132 EXTENDED_ARG         (256)
            1134 JUMP_ABSOLUTE        (to 504)

430:     >> 1136 LOAD_NAME            (oo000O0oOO)
            1138 LOAD_CONST           ("infoExtra")
            1140 COMPARE_OP           (==)
            1142 EXTENDED_ARG         (1280)
            1144 POP_JUMP_IF_FALSE    (to 1478)
            1146 LOAD_NAME            (o0OOo0)
            1148 EXTENDED_ARG         (1280)
            1150 POP_JUMP_IF_FALSE    (to 1478)

432:        1152 LOAD_CONST           (0)
            1154 LOAD_CONST           (('Tmdb',))
            1156 IMPORT_NAME          (libs.ioiiiIIIiI)
            1158 IMPORT_FROM          (Tmdb)
            1160 STORE_NAME           (Tmdb)
            1162 POP_TOP

433:        1164 LOAD_NAME            (o0OOo0)
            1166 LOAD_CONST           ("clear")
            1168 COMPARE_OP           (==)
            1170 EXTENDED_ARG         (1024)
            1172 POP_JUMP_IF_FALSE    (to 1188)

434:        1174 LOAD_NAME            (Tmdb)
            1176 CALL_FUNCTION        (0 positional arguments)
            1178 LOAD_METHOD          (clearInfoExtra)
            1180 CALL_METHOD          (0 positional arguments)
            1182 POP_TOP
            1184 EXTENDED_ARG         (256)
            1186 JUMP_FORWARD         (to 1468)

436:     >> 1188 LOAD_CONST           (None)
            1190 STORE_NAME           (I111iI11i)

437:        1192 LOAD_NAME            (o0OOo0)
            1194 LOAD_METHOD          (strip)
            1196 CALL_METHOD          (0 positional arguments)
            1198 LOAD_METHOD          (split)
            1200 LOAD_CONST           ("_")
            1202 CALL_METHOD          (1 positional argument)
            1204 UNPACK_SEQUENCE      2
            1206 STORE_NAME           (OooOoO0o00)
            1208 STORE_NAME           (i1II1)

438:        1210 LOAD_NAME            (OooOoO0o00)
            1212 EXTENDED_ARG         (1280)
            1214 POP_JUMP_IF_FALSE    (to 1468)
            1216 LOAD_NAME            (i1II1)
            1218 EXTENDED_ARG         (1280)
            1220 POP_JUMP_IF_FALSE    (to 1468)

439:        1222 LOAD_NAME            (OooOoO0o00)
            1224 LOAD_METHOD          (startswith)
            1226 LOAD_CONST           ("E")
            1228 CALL_METHOD          (1 positional argument)
            1230 EXTENDED_ARG         (1280)
            1232 POP_JUMP_IF_FALSE    (to 1314)

441:        1234 SETUP_FINALLY        (to 1294)

442:        1236 LOAD_NAME            (OooOoO0o00)
            1238 LOAD_CONST           (1)
            1240 LOAD_CONST           (None)
            1242 BUILD_SLICE          2
            1244 BINARY_SUBSCR
            1246 STORE_NAME           (oo00OOO)

443:        1248 LOAD_CONST           ('{"jsonrpc": "2.0", "method": "VideoLibrary.GetTVShowDetails", "params": {"tvshowid": %s, "properties": ["uniqueid"]}, "id": 1}')
            1250 LOAD_NAME            (oo00OOO)
            1252 BINARY_MODULO
            1254 STORE_NAME           (I11I111Ii)

444:        1256 LOAD_NAME            (load_json)
            1258 LOAD_NAME            (xbmc)
            1260 LOAD_METHOD          (executeJSONRPC)
            1262 LOAD_NAME            (I11I111Ii)
            1264 CALL_METHOD          (1 positional argument)
            1266 CALL_FUNCTION        (1 positional argument)
            1268 STORE_NAME           (II1Ii11111)

445:        1270 LOAD_NAME            (II1Ii11111)
            1272 LOAD_CONST           ("result")
            1274 BINARY_SUBSCR
            1276 LOAD_CONST           ("tvshowdetails")
            1278 BINARY_SUBSCR
            1280 LOAD_CONST           ("uniqueid")
            1282 BINARY_SUBSCR
            1284 LOAD_CONST           ("tmdb")
            1286 BINARY_SUBSCR
            1288 STORE_NAME           (OooOoO0o00)
            1290 POP_BLOCK
            1292 JUMP_FORWARD         (to 1314)

446:     >> 1294 POP_TOP
            1296 POP_TOP
            1298 POP_TOP

447:        1300 LOAD_NAME            (exit)
            1302 LOAD_CONST           (0)
            1304 CALL_FUNCTION        (1 positional argument)
            1306 POP_TOP

448:        1308 POP_EXCEPT
            1310 JUMP_FORWARD         (to 1314)
            1312 END_FINALLY

449:     >> 1314 LOAD_NAME            (i1II1)
            1316 LOAD_CONST           ("movie")
            1318 COMPARE_OP           (==)
            1320 EXTENDED_ARG         (1280)
            1322 POP_JUMP_IF_FALSE    (to 1428)

450:        1324 LOAD_NAME            (Watched)
            1326 CALL_FUNCTION        (0 positional arguments)
            1328 SETUP_WITH           (to 1356)
            1330 STORE_NAME           (I11I1iI)

451:        1332 LOAD_NAME            (I11I1iI)
            1334 LOAD_METHOD          (getProgressMovies)
            1336 LOAD_NAME            (OooOoO0o00)
            1338 CALL_METHOD          (1 positional argument)
            1340 LOAD_METHOD          (get)
            1342 LOAD_NAME            (int)
            1344 LOAD_NAME            (OooOoO0o00)
            1346 CALL_FUNCTION        (1 positional argument)
            1348 CALL_METHOD          (1 positional argument)
            1350 STORE_NAME           (iiiI)
            1352 POP_BLOCK
            1354 BEGIN_FINALLY
         >> 1356 WITH_CLEANUP_START
            1358 WITH_CLEANUP_FINISH
            1360 END_FINALLY

452:        1362 LOAD_NAME            (iiiI)
            1364 EXTENDED_ARG         (1280)
            1366 POP_JUMP_IF_FALSE    (to 1452)

453:        1368 LOAD_NAME            (int)
            1370 LOAD_NAME            (iiiI)
            1372 LOAD_CONST           (2)
            1374 BINARY_SUBSCR
            1376 CALL_FUNCTION        (1 positional argument)
            1378 LOAD_NAME            (float)
            1380 LOAD_NAME            (iiiI)
            1382 LOAD_CONST           (1)
            1384 BINARY_SUBSCR
            1386 CALL_FUNCTION        (1 positional argument)
            1388 BINARY_MULTIPLY
            1390 LOAD_CONST           (100)
            1392 BINARY_TRUE_DIVIDE
            1394 STORE_NAME           (I111iI11i)

454:        1396 LOAD_CONST           ("0")
            1398 LOAD_NAME            (str)
            1400 LOAD_NAME            (datetime)
            1402 LOAD_ATTR            (timedelta)
            1404 LOAD_NAME            (I111iI11i)
            1406 LOAD_CONST           (('seconds',))
            1408 CALL_FUNCTION_KW     (1 total positional and keyword args)
            1410 CALL_FUNCTION        (1 positional argument)
            1412 LOAD_METHOD          (split)
            1414 LOAD_CONST           (".")
            1416 CALL_METHOD          (1 positional argument)
            1418 LOAD_CONST           (0)
            1420 BINARY_SUBSCR
            1422 BINARY_ADD
            1424 STORE_NAME           (iI1i1Iiii11i)
            1426 JUMP_FORWARD         (to 1452)

455:     >> 1428 LOAD_NAME            (i1II1)
            1430 LOAD_CONST           (('tvshow', 'season', 'episode'))
            1432 COMPARE_OP           (in)
            1434 EXTENDED_ARG         (1280)
            1436 POP_JUMP_IF_FALSE    (to 1444)

456:        1438 LOAD_CONST           ("tv")
            1440 STORE_NAME           (i1II1)
            1442 JUMP_FORWARD         (to 1452)

458:     >> 1444 LOAD_NAME            (exit)
            1446 LOAD_CONST           (0)
            1448 CALL_FUNCTION        (1 positional argument)
            1450 POP_TOP

459:     >> 1452 LOAD_NAME            (Tmdb)
            1454 CALL_FUNCTION        (0 positional arguments)
            1456 LOAD_METHOD          (getInfoExtra)
            1458 LOAD_NAME            (OooOoO0o00)
            1460 LOAD_NAME            (i1II1)
            1462 LOAD_NAME            (I111iI11i)
            1464 CALL_METHOD          (3 positional arguments)
            1466 POP_TOP

460:     >> 1468 LOAD_NAME            (exit)
            1470 LOAD_CONST           (0)
            1472 CALL_FUNCTION        (1 positional argument)
            1474 POP_TOP

461:        1476 JUMP_FORWARD         (to 1694)

462:     >> 1478 LOAD_NAME            (oo000O0oOO)
            1480 LOAD_CONST           ("contextMenu")
            1482 COMPARE_OP           (==)
            1484 EXTENDED_ARG         (1280)
            1486 POP_JUMP_IF_FALSE    (to 1528)
            1488 LOAD_NAME            (o0OOo0)
            1490 EXTENDED_ARG         (1280)
            1492 POP_JUMP_IF_FALSE    (to 1528)

463:        1494 LOAD_NAME            (o0OOo0)
            1496 LOAD_METHOD          (replace)
            1498 LOAD_CONST           ("plugin://plugin.video.palantir3/?")
            1500 LOAD_CONST           ("")
            1502 CALL_METHOD          (2 positional arguments)
            1504 STORE_NAME           (ooOOoO00OO)

464:        1506 LOAD_NAME            (ContextMenu)
            1508 LOAD_NAME            (ooOOoO00OO)
            1510 CALL_FUNCTION        (1 positional argument)
            1512 LOAD_METHOD          (show)
            1514 CALL_METHOD          (0 positional arguments)
            1516 POP_TOP

465:        1518 LOAD_NAME            (exit)
            1520 LOAD_CONST           (0)
            1522 CALL_FUNCTION        (1 positional argument)
            1524 POP_TOP

466:        1526 JUMP_FORWARD         (to 1694)

467:     >> 1528 LOAD_NAME            (oo000O0oOO)
            1530 LOAD_CONST           ("addRating")
            1532 COMPARE_OP           (==)
            1534 EXTENDED_ARG         (1536)
            1536 POP_JUMP_IF_FALSE    (to 1616)
            1538 LOAD_NAME            (len)
            1540 LOAD_NAME            (o0OOo0)
            1542 LOAD_METHOD          (split)
            1544 LOAD_CONST           ("_")
            1546 CALL_METHOD          (1 positional argument)
            1548 CALL_FUNCTION        (1 positional argument)
            1550 LOAD_CONST           (3)
            1552 COMPARE_OP           (==)
            1554 EXTENDED_ARG         (1536)
            1556 POP_JUMP_IF_FALSE    (to 1616)

468:        1558 LOAD_CONST           (0)
            1560 LOAD_CONST           (('Trakt',))
            1562 IMPORT_NAME          (libs.ioIIiII11)
            1564 IMPORT_FROM          (Trakt)
            1566 STORE_NAME           (Trakt)
            1568 POP_TOP

470:        1570 LOAD_NAME            (o0OOo0)
            1572 LOAD_METHOD          (split)
            1574 LOAD_CONST           ("_")
            1576 CALL_METHOD          (1 positional argument)
            1578 UNPACK_SEQUENCE      3
            1580 STORE_NAME           (O0ooOO0O0O0O)
            1582 STORE_NAME           (o00ooo0Oooo)
            1584 STORE_NAME           (oOO0)

471:        1586 LOAD_NAME            (Trakt)
            1588 CALL_FUNCTION        (0 positional arguments)
            1590 LOAD_ATTR            (addRatings)
            1592 LOAD_NAME            (O0ooOO0O0O0O)
            1594 LOAD_NAME            (o00ooo0Oooo)
            1596 LOAD_NAME            (oOO0)
            1598 LOAD_CONST           (True)
            1600 LOAD_CONST           (('forzado',))
            1602 CALL_FUNCTION_KW     (4 total positional and keyword args)
            1604 POP_TOP

472:        1606 LOAD_NAME            (exit)
            1608 LOAD_CONST           (0)
            1610 CALL_FUNCTION        (1 positional argument)
            1612 POP_TOP

473:        1614 JUMP_FORWARD         (to 1694)

474:     >> 1616 LOAD_NAME            (oo000O0oOO)
            1618 LOAD_CONST           ("findByActor")
            1620 COMPARE_OP           (==)
            1622 EXTENDED_ARG         (256)
            1624 POP_JUMP_IF_FALSE    (to 504)
            1626 LOAD_NAME            (len)
            1628 LOAD_NAME            (o0OOo0)
            1630 LOAD_METHOD          (split)
            1632 LOAD_CONST           ("_")
            1634 CALL_METHOD          (1 positional argument)
            1636 CALL_FUNCTION        (1 positional argument)
            1638 LOAD_CONST           (2)
            1640 COMPARE_OP           (==)
            1642 EXTENDED_ARG         (256)
            1644 POP_JUMP_IF_FALSE    (to 504)

475:        1646 LOAD_NAME            (o0OOo0)
            1648 LOAD_METHOD          (split)
            1650 LOAD_CONST           ("_")
            1652 CALL_METHOD          (1 positional argument)
            1654 UNPACK_SEQUENCE      2
            1656 STORE_NAME           (OOoOo)
            1658 STORE_NAME           (O0ooOO0O0O0O)

476:        1660 LOAD_NAME            (xbmc)
            1662 LOAD_METHOD          (executebuiltin)
            1664 LOAD_CONST           ("Dialog.Close(movieinformation,force)")
            1666 CALL_METHOD          (1 positional argument)
            1668 POP_TOP

477:        1670 LOAD_NAME            (P3Item)
            1672 LOAD_CONST           ("listado_content_actor")
            1674 LOAD_NAME            (O0ooOO0O0O0O)
            1676 LOAD_NAME            (OOoOo)
            1678 LOAD_CONST           (('action', 'content', 'actorID'))
            1680 CALL_FUNCTION_KW     (3 total positional and keyword args)
            1682 LOAD_METHOD          (tourl)
            1684 CALL_METHOD          (0 positional arguments)
            1686 LOAD_NAME            (sys)
            1688 LOAD_ATTR            (argv)
            1690 LOAD_CONST           (2)
            1692 STORE_SUBSCR

480:     >> 1694 EXTENDED_ARG         (256)
            1696 JUMP_ABSOLUTE        (to 504)

481:     >> 1698 LOAD_NAME            (sys)
            1700 LOAD_ATTR            (argv)
            1702 LOAD_CONST           (2)
            1704 BINARY_SUBSCR
            1706 LOAD_METHOD          (split)
            1708 LOAD_CONST           ("&")
            1710 CALL_METHOD          (1 positional argument)
            1712 LOAD_CONST           (0)
            1714 BINARY_SUBSCR
            1716 LOAD_NAME            (sys)
            1718 LOAD_ATTR            (argv)
            1720 LOAD_CONST           (2)
            1722 STORE_SUBSCR

483:     >> 1724 LOAD_NAME            (P3Item)
            1726 CALL_FUNCTION        (0 positional arguments)
            1728 LOAD_METHOD          (fromurl)
            1730 LOAD_NAME            (sys)
            1732 LOAD_ATTR            (argv)
            1734 LOAD_CONST           (2)
            1736 BINARY_SUBSCR
            1738 CALL_METHOD          (1 positional argument)
            1740 STORE_NAME           (ooOooo)

485:        1742 LOAD_NAME            (O0oO0Ooo)
            1744 EXTENDED_ARG         (1536)
            1746 POP_JUMP_IF_FALSE    (to 1756)

486:        1748 LOAD_NAME            (O0oO0Ooo)
            1750 LOAD_NAME            (ooOooo)
            1752 STORE_ATTR           (limitItemList)
            1754 JUMP_FORWARD         (to 1774)

487:     >> 1756 LOAD_NAME            (ooOooo)
            1758 LOAD_ATTR            (limitItemList)
            1760 EXTENDED_ARG         (1536)
            1762 POP_JUMP_IF_TRUE     (to 1774)

488:        1764 LOAD_NAME            (get_setting)
            1766 LOAD_CONST           ("limitItemList")
            1768 CALL_FUNCTION        (1 positional argument)
            1770 LOAD_NAME            (ooOooo)
            1772 STORE_ATTR           (limitItemList)

490:     >> 1774 LOAD_CONST           ("percentPlayed")
            1776 LOAD_NAME            (ooOooo)
            1778 LOAD_ATTR            (__dict__)
            1780 COMPARE_OP           (in)
            1782 EXTENDED_ARG         (1792)
            1784 POP_JUMP_IF_FALSE    (to 2042)
            1786 LOAD_NAME            (float)
            1788 LOAD_NAME            (ooOooo)
            1790 LOAD_ATTR            (percentPlayed)
            1792 CALL_FUNCTION        (1 positional argument)
            1794 LOAD_CONST           (0.0)
            1796 COMPARE_OP           (>)
            1798 EXTENDED_ARG         (1792)
            1800 POP_JUMP_IF_FALSE    (to 2042)
            1802 LOAD_NAME            (ooOooo)
            1804 LOAD_ATTR            (playContext)
            1806 EXTENDED_ARG         (1792)
            1808 POP_JUMP_IF_TRUE     (to 2042)
            1810 LOAD_NAME            (Ii1iIII11i)
            1812 EXTENDED_ARG         (1792)
            1814 POP_JUMP_IF_TRUE     (to 2042)
            1816 LOAD_NAME            (len)
            1818 LOAD_NAME            (sys)
            1820 LOAD_ATTR            (argv)
            1822 CALL_FUNCTION        (1 positional argument)
            1824 LOAD_CONST           (3)
            1826 COMPARE_OP           (>)
            1828 EXTENDED_ARG         (1792)
            1830 POP_JUMP_IF_FALSE    (to 2042)
            1832 LOAD_CONST           ("resume:false")
            1834 LOAD_NAME            (sys)
            1836 LOAD_ATTR            (argv)
            1838 LOAD_CONST           (3)
            1840 LOAD_CONST           (None)
            1842 BUILD_SLICE          2
            1844 BINARY_SUBSCR
            1846 COMPARE_OP           (in)
            1848 EXTENDED_ARG         (1792)
            1850 POP_JUMP_IF_FALSE    (to 2042)

493:        1852 LOAD_NAME            (ooOooo)
            1854 LOAD_METHOD          (pop)
            1856 LOAD_CONST           ("percentPlayed")
            1858 CALL_METHOD          (1 positional argument)
            1860 POP_TOP

494:        1862 LOAD_NAME            (Watched)
            1864 CALL_FUNCTION        (0 positional arguments)
            1866 SETUP_WITH           (to 1922)
            1868 STORE_NAME           (I11I1iI)

495:        1870 LOAD_NAME            (I11I1iI)
            1872 LOAD_METHOD          (markAsUnwatched)
            1874 LOAD_NAME            (ooOooo)
            1876 LOAD_ATTR            (content)

496:        1878 LOAD_NAME            (ooOooo)
            1880 LOAD_ATTR            (tmdb)

497:        1882 LOAD_NAME            (ooOooo)
            1884 LOAD_ATTR            (season)
            1886 EXTENDED_ARG         (1792)
            1888 POP_JUMP_IF_FALSE    (to 1896)
            1890 LOAD_NAME            (ooOooo)
            1892 LOAD_ATTR            (season)
            1894 JUMP_FORWARD         (to 1898)
         >> 1896 LOAD_CONST           (None)

498:     >> 1898 LOAD_NAME            (ooOooo)
            1900 LOAD_ATTR            (episode)
            1902 EXTENDED_ARG         (1792)
            1904 POP_JUMP_IF_FALSE    (to 1912)
            1906 LOAD_NAME            (ooOooo)
            1908 LOAD_ATTR            (episode)
            1910 JUMP_FORWARD         (to 1914)
         >> 1912 LOAD_CONST           (None)

495:     >> 1914 CALL_METHOD          (4 positional arguments)
            1916 POP_TOP

499:        1918 POP_BLOCK
            1920 BEGIN_FINALLY
         >> 1922 WITH_CLEANUP_START
            1924 WITH_CLEANUP_FINISH
            1926 END_FINALLY
            1928 JUMP_FORWARD         (to 2042)

501:     >> 1930 LOAD_NAME            (WINDOW)
            1932 LOAD_METHOD          (getProperty)
            1934 LOAD_CONST           ("p3UpdateLock")
            1936 CALL_METHOD          (1 positional argument)
            1938 LOAD_CONST           ("true")
            1940 COMPARE_OP           (!=)
            1942 EXTENDED_ARG         (1792)
            1944 POP_JUMP_IF_FALSE    (to 2006)

502:        1946 LOAD_NAME            (WINDOW)
            1948 LOAD_METHOD          (setProperty)
            1950 LOAD_CONST           ("p3UpdateLock")
            1952 LOAD_CONST           ("true")
            1954 CALL_METHOD          (2 positional arguments)
            1956 POP_TOP

504:        1958 SETUP_FINALLY        (to 1994)

505:        1960 LOAD_NAME            (oOo0O00O0ooo)
            1962 CALL_FUNCTION        (0 positional arguments)
            1964 POP_TOP

508:        1966 LOAD_NAME            (Thread)
            1968 LOAD_NAME            (iii1i1iiIi1)
            1970 LOAD_CONST           (('target',))
            1972 CALL_FUNCTION_KW     (1 total positional and keyword args)
            1974 STORE_NAME           (Oo0O0O)

509:        1976 LOAD_CONST           (True)
            1978 LOAD_NAME            (Oo0O0O)
            1980 STORE_ATTR           (daemon)

510:        1982 LOAD_NAME            (Oo0O0O)
            1984 LOAD_METHOD          (start)
            1986 CALL_METHOD          (0 positional arguments)
            1988 POP_TOP
            1990 POP_BLOCK
            1992 BEGIN_FINALLY

512:     >> 1994 LOAD_NAME            (WINDOW)
            1996 LOAD_METHOD          (clearProperty)
            1998 LOAD_CONST           ("p3UpdateLock")
            2000 CALL_METHOD          (1 positional argument)
            2002 POP_TOP

513:        2004 END_FINALLY

514:     >> 2006 LOAD_NAME            (P3Item)

515:        2008 LOAD_CONST           ("special://home/addons/plugin.video.palantir3/icon.png")

516:        2010 LOAD_CONST           ("special://home/addons/plugin.video.palantir3/fanart.gif")

517:        2012 LOAD_NAME            (xbmc)
            2014 LOAD_METHOD          (getSkinDir)
            2016 CALL_METHOD          (0 positional arguments)
            2018 LOAD_METHOD          (startswith)
            2020 LOAD_CONST           ("skin.estuary")
            2022 CALL_METHOD          (1 positional argument)
            2024 EXTENDED_ARG         (1792)
            2026 POP_JUMP_IF_TRUE     (to 2032)
            2028 LOAD_CONST           ("files")
            2030 JUMP_FORWARD         (to 2034)
         >> 2032 LOAD_CONST           ("albums")

518:     >> 2034 LOAD_CONST           ("select label,action,icon,sql,fanart from menus where menu_id = 10 ORDER by item_id asc")

514:        2036 LOAD_CONST           (('icon', 'fanart', 'content', 'sql'))
            2038 CALL_FUNCTION_KW     (4 total positional and keyword args)
            2040 STORE_NAME           (ooOooo)

521:     >> 2042 LOAD_NAME            (IIiI1i)
            2044 LOAD_NAME            (ooOooo)
            2046 CALL_FUNCTION        (1 positional argument)
            2048 POP_TOP

522:     >> 2050 LOAD_CONST           (None)
            2052 RETURN_VALUE


# Method Name:       I1i
# Filename:          <string>
# Argument count:    5
# Position-only argument count: 0
# Keyword-only arguments: 0
# Number of locals:  15
# Stack size:        9
# Flags:             0x00000043 (NOFREE | NEWLOCALS | OPTIMIZED)
# First Line:        21
# Constants:
#    0: None
#    1: <Code38 code object IiI11Ii111 at 0x1624c515410, file <string>>, line 22
#    2: 'IiI11Ii111'
#    3: <Code38 code object iIi at 0x1624c514850, file <string>>, line 34
#    4: 'iIi'
#    5: 'libs.'
#    6: 'Path'
#    7: '.'
#    8: '.md'
#    9: 'rb'
#   10: 3
#   11: -1
#   12: 'utf-8'
# Names:
#    0: abc
#    1: Loader
#    2: MetaPathFinder
#    3: sys
#    4: modules
#    5: startswith
#    6: os
#    7: path
#    8: join
#    9: xbmcvfs
#   10: translatePath
#   11: xbmcaddon
#   12: Addon
#   13: getAddonInfo
#   14: replace
#   15: sep
#   16: isfile
#   17: open
#   18: read
#   19: len
#   20: iI111iiIi11i
#   21: decode
#   22: meta_path
#   23: append
#   24: OoOoo0o
# Varnames:
#	name, locals, globals, fromlist, level, IiI11Ii111, iIi, ii, iiI, i1Ii1i, oOooo0OOO, Oo000ooO0Oooo, IIiI, oO0, i1iiiiIIIiIi
# Positional arguments:
#	name, locals, globals, fromlist, level
# Local variables:
#    5: IiI11Ii111
#    6: iIi
#    7: ii
#    8: iiI
#    9: i1Ii1i
#   10: oOooo0OOO
#   11: Oo000ooO0Oooo
#   12: IIiI
#   13: oO0
#   14: i1iiiiIIIiIi

 22:           0 LOAD_BUILD_CLASS
               2 LOAD_CONST           (<Code38 code object IiI11Ii111 at 0x1624c515410, file <string>>, line 22)
               4 LOAD_CONST           ("IiI11Ii111")
               6 MAKE_FUNCTION        (No arguments)
               8 LOAD_CONST           ("IiI11Ii111")
              10 LOAD_GLOBAL          (abc)
              12 LOAD_ATTR            (Loader)
              14 CALL_FUNCTION        (3 positional arguments)
              16 STORE_FAST           (IiI11Ii111)

 34:          18 LOAD_BUILD_CLASS
              20 LOAD_CONST           (<Code38 code object iIi at 0x1624c514850, file <string>>, line 34)
              22 LOAD_CONST           ("iIi")
              24 MAKE_FUNCTION        (No arguments)
              26 LOAD_CONST           ("iIi")
              28 LOAD_GLOBAL          (abc)
              30 LOAD_ATTR            (MetaPathFinder)
              32 CALL_FUNCTION        (3 positional arguments)
              34 STORE_FAST           (iIi)

 40:          36 LOAD_FAST            (name)
              38 LOAD_GLOBAL          (sys)
              40 LOAD_ATTR            (modules)
              42 COMPARE_OP           (not-in)
              44 EXTENDED_ARG         (256)
              46 POP_JUMP_IF_FALSE    (to 278)
              48 LOAD_FAST            (name)
              50 LOAD_METHOD          (startswith)
              52 LOAD_CONST           ("libs.")
              54 CALL_METHOD          (1 positional argument)
              56 EXTENDED_ARG         (256)
              58 POP_JUMP_IF_FALSE    (to 278)

 41:          60 LOAD_GLOBAL          (os)
              62 LOAD_ATTR            (path)
              64 LOAD_METHOD          (join)
              66 LOAD_GLOBAL          (xbmcvfs)
              68 LOAD_METHOD          (translatePath)
              70 LOAD_GLOBAL          (xbmcaddon)
              72 LOAD_METHOD          (Addon)
              74 CALL_METHOD          (0 positional arguments)
              76 LOAD_METHOD          (getAddonInfo)
              78 LOAD_CONST           ("Path")
              80 CALL_METHOD          (1 positional argument)
              82 CALL_METHOD          (1 positional argument)
              84 LOAD_FAST            (name)
              86 LOAD_METHOD          (replace)
              88 LOAD_CONST           (".")
              90 LOAD_GLOBAL          (os)
              92 LOAD_ATTR            (path)
              94 LOAD_ATTR            (sep)
              96 CALL_METHOD          (2 positional arguments)
              98 LOAD_CONST           (".md")
             100 BINARY_ADD
             102 CALL_METHOD          (2 positional arguments)
             104 STORE_FAST           (ii)

 42:         106 LOAD_GLOBAL          (os)
             108 LOAD_ATTR            (path)
             110 LOAD_METHOD          (isfile)
             112 LOAD_FAST            (ii)
             114 CALL_METHOD          (1 positional argument)
             116 EXTENDED_ARG         (256)
             118 POP_JUMP_IF_FALSE    (to 278)

 43:         120 LOAD_GLOBAL          (open)
             122 LOAD_FAST            (ii)
             124 LOAD_CONST           ("rb")
             126 CALL_FUNCTION        (2 positional arguments)
             128 SETUP_WITH           (to 144)
             130 STORE_FAST           (iiI)

 44:         132 LOAD_FAST            (iiI)
             134 LOAD_METHOD          (read)
             136 CALL_METHOD          (0 positional arguments)
             138 STORE_FAST           (i1Ii1i)
             140 POP_BLOCK
             142 BEGIN_FINALLY
         >>  144 WITH_CLEANUP_START
             146 WITH_CLEANUP_FINISH
             148 END_FINALLY

 45:         150 LOAD_GLOBAL          (len)
             152 LOAD_FAST            (i1Ii1i)
             154 CALL_FUNCTION        (1 positional argument)
             156 STORE_FAST           (oOooo0OOO)

 46:         158 LOAD_FAST            (oOooo0OOO)
             160 LOAD_CONST           (3)
             162 BINARY_FLOOR_DIVIDE
             164 STORE_FAST           (Oo000ooO0Oooo)

 47:         166 LOAD_FAST            (i1Ii1i)
             168 LOAD_FAST            (oOooo0OOO)
             170 LOAD_FAST            (Oo000ooO0Oooo)
             172 BINARY_SUBTRACT
             174 LOAD_CONST           (None)
             176 BUILD_SLICE          2
             178 BINARY_SUBSCR
             180 STORE_FAST           (IIiI)

 48:         182 LOAD_FAST            (i1Ii1i)
             184 LOAD_CONST           (None)
             186 LOAD_FAST            (oOooo0OOO)
             188 LOAD_FAST            (Oo000ooO0Oooo)
             190 BINARY_SUBTRACT
             192 BUILD_SLICE          2
             194 BINARY_SUBSCR
             196 STORE_FAST           (i1Ii1i)

 49:         198 LOAD_FAST            (IIiI)
             200 LOAD_FAST            (i1Ii1i)
             202 LOAD_CONST           (None)
             204 LOAD_FAST            (Oo000ooO0Oooo)
             206 BUILD_SLICE          2
             208 BINARY_SUBSCR
             210 LOAD_FAST            (i1Ii1i)
             212 LOAD_FAST            (Oo000ooO0Oooo)
             214 LOAD_CONST           (None)
             216 BUILD_SLICE          2
             218 BINARY_SUBSCR
             220 LOAD_CONST           (None)
             222 LOAD_CONST           (None)
             224 LOAD_CONST           (-1)
             226 BUILD_SLICE          3
             228 BINARY_SUBSCR
             230 BINARY_ADD
             232 INPLACE_ADD
             234 STORE_FAST           (IIiI)

 50:         236 LOAD_FAST            (name)
             238 LOAD_GLOBAL          (iI111iiIi11i)
             240 LOAD_FAST            (IIiI)
             242 CALL_FUNCTION        (1 positional argument)
             244 LOAD_METHOD          (decode)
             246 LOAD_CONST           ("utf-8")
             248 CALL_METHOD          (1 positional argument)
             250 BUILD_MAP            1
             252 STORE_FAST           (oO0)

 51:         254 LOAD_FAST            (iIi)
             256 LOAD_FAST            (IiI11Ii111)
             258 LOAD_FAST            (oO0)
             260 CALL_FUNCTION        (1 positional argument)
             262 CALL_FUNCTION        (1 positional argument)
             264 STORE_FAST           (i1iiiiIIIiIi)

 52:         266 LOAD_GLOBAL          (sys)
             268 LOAD_ATTR            (meta_path)
             270 LOAD_METHOD          (append)
             272 LOAD_FAST            (i1iiiiIIIiIi)
             274 CALL_METHOD          (1 positional argument)
             276 POP_TOP

 53:     >>  278 LOAD_GLOBAL          (OoOoo0o)
             280 LOAD_FAST            (name)
             282 LOAD_FAST            (locals)
             284 LOAD_FAST            (globals)
             286 LOAD_FAST            (fromlist)
             288 LOAD_FAST            (level)
             290 CALL_FUNCTION        (5 positional arguments)
             292 RETURN_VALUE


# Method Name:       I1ii1111IIi
# Filename:          <string>
# Argument count:    2
# Position-only argument count: 0
# Keyword-only arguments: 0
# Number of locals:  6
# Stack size:        10
# Flags:             0x00000043 (NOFREE | NEWLOCALS | OPTIMIZED)
# First Line:        64
# Constants:
#    0: None
#    1: 'p3download_videoLock'
#    2: 'true'
#    3: 'true'
#    4: 'download video...'
#    5: 'wb'
#    6: 'video_intro'
#    7: 'download_video: %s'
#    8: 'error'
# Names:
#    0: WINDOW
#    1: getProperty
#    2: setProperty
#    3: i1
#    4: ooo000
#    5: oOo0O00
#    6: i1iiIII111
#    7: Iii1i
#    8: requests
#    9: clearProperty
#   10: o0i1i
#   11: I1I
#   12: OOO00000O
#   13: ooOOO
#   14: i1i1i1111I
#   15: Ii
#   16: logger
#   17: get
#   18: Ii111
#   19: raise_for_status
#   20: open
#   21: write
#   22: content
#   23: OooOoo
#   24: set_setting
#   25: Exception
#   26: str
# Varnames:
#	url, video_path, requests, ii1IiIiiII, iiI, o00
# Positional arguments:
#	url, video_path
# Local variables:
#    2: requests
#    3: ii1IiIiiII
#    4: iiI
#    5: o00

 65:           0 LOAD_GLOBAL          (WINDOW)
               2 LOAD_METHOD          (getProperty)
               4 LOAD_CONST           ("p3download_videoLock")
               6 CALL_METHOD          (1 positional argument)
               8 LOAD_CONST           ("true")
              10 COMPARE_OP           (!=)
              12 POP_JUMP_IF_FALSE    (to 180)

 66:          14 LOAD_GLOBAL          (WINDOW)
              16 LOAD_METHOD          (setProperty)
              18 LOAD_CONST           ("p3download_videoLock")
              20 LOAD_CONST           ("true")
              22 CALL_METHOD          (2 positional arguments)
              24 POP_TOP

 68:          26 LOAD_CONST           ("true")
              28 LOAD_CONST           (None)
              30 IMPORT_NAME          (requests)
              32 STORE_FAST           (requests)

 69:          34 SETUP_FINALLY        (to 168)
              36 SETUP_FINALLY        (to 112)

 70:          38 LOAD_GLOBAL          (logger)
              40 LOAD_CONST           ("download video...")
              42 CALL_FUNCTION        (1 positional argument)
              44 POP_TOP

 71:          46 LOAD_FAST            (requests)
              48 LOAD_METHOD          (get)
              50 LOAD_FAST            (url)
              52 CALL_METHOD          (1 positional argument)
              54 STORE_FAST           (ii1IiIiiII)

 73:          56 LOAD_FAST            (ii1IiIiiII)
              58 LOAD_METHOD          (raise_for_status)
              60 CALL_METHOD          (0 positional arguments)
              62 POP_TOP

 74:          64 LOAD_GLOBAL          (open)
              66 LOAD_FAST            (video_path)
              68 LOAD_CONST           ("wb")
              70 CALL_FUNCTION        (2 positional arguments)
              72 SETUP_WITH           (to 92)
              74 STORE_FAST           (iiI)

 75:          76 LOAD_FAST            (iiI)
              78 LOAD_METHOD          (write)
              80 LOAD_FAST            (ii1IiIiiII)
              82 LOAD_ATTR            (content)
              84 CALL_METHOD          (1 positional argument)
              86 POP_TOP

 76:          88 POP_BLOCK
              90 BEGIN_FINALLY
         >>   92 WITH_CLEANUP_START
              94 WITH_CLEANUP_FINISH
              96 END_FINALLY

 77:          98 LOAD_GLOBAL          (set_setting)
             100 LOAD_CONST           ("video_intro")
             102 LOAD_FAST            (url)
             104 CALL_FUNCTION        (2 positional arguments)
             106 POP_TOP
             108 POP_BLOCK
             110 JUMP_FORWARD         (to 164)

 78:     >>  112 DUP_TOP
             114 LOAD_GLOBAL          (Exception)
             116 COMPARE_OP           (exception-match)
             118 POP_JUMP_IF_FALSE    (to 162)
             120 POP_TOP
             122 STORE_FAST           (o00)
             124 POP_TOP
             126 SETUP_FINALLY        (to 150)

 79:         128 LOAD_GLOBAL          (logger)
             130 LOAD_CONST           ("download_video: %s")
             132 LOAD_GLOBAL          (str)
             134 LOAD_FAST            (o00)
             136 CALL_FUNCTION        (1 positional argument)
             138 BINARY_MODULO
             140 LOAD_CONST           ("error")
             142 CALL_FUNCTION        (2 positional arguments)
             144 POP_TOP
             146 POP_BLOCK
             148 BEGIN_FINALLY
         >>  150 LOAD_CONST           (None)
             152 STORE_FAST           (o00)
             154 DELETE_FAST          (o00)
             156 END_FINALLY
             158 POP_EXCEPT
             160 JUMP_FORWARD         (to 164)
         >>  162 END_FINALLY
         >>  164 POP_BLOCK
             166 BEGIN_FINALLY

 81:     >>  168 LOAD_GLOBAL          (WINDOW)
             170 LOAD_METHOD          (clearProperty)
             172 LOAD_CONST           ("p3download_videoLock")
             174 CALL_METHOD          (1 positional argument)
             176 POP_TOP

 83:         178 END_FINALLY
         >>  180 LOAD_CONST           (None)
             182 RETURN_VALUE


# Method Name:       oOo0O00O0ooo
# Filename:          <string>
# Argument count:    0
# Position-only argument count: 0
# Keyword-only arguments: 0
# Number of locals:  32
# Stack size:        14
# Flags:             0x00000043 (NOFREE | NEWLOCALS | OPTIMIZED)
# First Line:        84
# Constants:
#    0: None
#    1: False
#    2: 'special://home/addons/plugin.video.palantir3/moria.cm3'
#    3: 'PalCO'
#    4: 10
#    5: True
#    6: 'last_up'
#    7: 19
#    8: '|'
#    9: '|'
#   10: 'update'
#   11: 1
#   12: '403'
#   13: 'for url'
#   14: 3000
#   15: '%s: %s'
#   16: 'error'
#   17: ('getDateUpdate', 'executeSelect')
#   18: 'No existe la base'
#   19: 'SELECT version, mensaje_inicial, mensaje_update, notificacion_update, video_intro from version ORDER by version DESC'
#   20: 'all'
#   21: 'select tmdb FROM enlaces_series group by tmdb,temporada,episodio;'
#   22: 'select * FROM pelis'
#   23: '\\\\n'
#   24: 30052
#   25: 5000
#   26: ('p3especialesname', 'p3especialespath', 'p3especiales2name', 'p3especiales2path')
#   27: 'SELECT label,action,sql from menus where sql like "%where coleccion like%" and menu_id > 0 and menu_id <= 100'
#   28: 'SELECT label,action,sql from menus where action = "listado_trakt" and menu_id > 0 and menu_id <= 100'
#   29: 'v_pelis'
#   30: 2
#   31: 'v_series'
#   32: 'p3especialesname'
#   33: 'p3especialespath'
#   34: 'plugin://plugin.video.palantir3/?'
#   35: 'WidgetEspeciales'
#   36: 'movies'
#   37: 'tvshows'
#   38: ('label', 'action', 'sql', 'isWidget', 'nameWidget', 'content')
#   39: 'p3especiales2name'
#   40: 'p3especiales2path'
#   41: 'WidgetEspeciales2'
#   42: 'special://profile/addon_data/skin.estuary.palantir/video_especial.mp4'
#   43: 'video_intro'
#   44: ''
#   45: ('target', 'args')
#   46: 'BBDD moria.cm3'
# Names:
#    0: IiIIii11Ii
#    1: oOo0O00
#    2: xbmcvfs
#    3: exists
#    4: getNameTempFile
#    5: get_setting
#    6: i1iiIII111
#    7: Oo
#    8: ooOOO
#    9: os
#   10: path
#   11: isfile
#   12: getsize
#   13: get_moria
#   14: o0i1i
#   15: OOO00000O
#   16: getDateUpdate
#   17: I1I
#   18: Ooo0Ooo
#   19: ooo000
#   20: Exception
#   21: str
#   22: split
#   23: len
#   24: i1i1i1111I
#   25: OooOoo
#   26: i1
#   27: xbmcgui
#   28: NOTIFICATION_ERROR
#   29: Dialog
#   30: notification
#   31: o00o
#   32: logger
#   33: iI1iII1I1I1i
#   34: MoriaDB
#   35: executeSelect
#   36: Watched
#   37: Iii1i
#   38: o0
#   39: CACHE
#   40: clear
#   41: setShowUpdated
#   42: I1Ii1I1
#   43: re
#   44: sub
#   45: linesep
#   46: localize
#   47: NOTIFICATION_INFO
#   48: IIiIIiIi11I1
#   49: Ii111
#   50: DialogImage
#   51: ISESTUARYPALANTIR
#   52: actualizarWidgetFavoritos
#   53: WINDOW
#   54: clearProperty
#   55: list
#   56: extend
#   57: append
#   58: setProperty
#   59: P3Item
#   60: tourl
#   61: translatePath
#   62: remove
#   63: set_setting
#   64: Thread
#   65: I1ii1111IIi
#   66: daemon
#   67: start
#   68: Ii
# Varnames:
#	i11iIii, OO, iiI1I11iiiiI, iII11iIi1iIiI, i1IIiII11, IiIi1Ii1111, o00, i1I11i11, OoOOoO000O, O0o0O0o0o, oO00o00OO, OOo0OOOo0O, oOo0Oo, O0ooooO, iII, OooOO00o, OOO00000oO, I11I1iI, OOoOo00o, oo0ooooo0ooo, I1iO0oo000o, oOo, OOOOOoo0oOo00, ooOo00o, o0oOoo0OOOOOoo, OoO, o00ooo0Oooo, oOOOO0OO00, i1iI1, OoOOo0oO000oOo0, O0o, Oo0O0O
# Local variables:
#    0: i11iIii
#    1: OO
#    2: iiI1I11iiiiI
#    3: iII11iIi1iIiI
#    4: i1IIiII11
#    5: IiIi1Ii1111
#    6: o00
#    7: i1I11i11
#    8: OoOOoO000O
#    9: O0o0O0o0o
#   10: oO00o00OO
#   11: OOo0OOOo0O
#   12: oOo0Oo
#   13: O0ooooO
#   14: iII
#   15: OooOO00o
#   16: OOO00000oO
#   17: I11I1iI
#   18: OOoOo00o
#   19: oo0ooooo0ooo
#   20: I1iO0oo000o
#   21: oOo
#   22: OOOOOoo0oOo00
#   23: ooOo00o
#   24: o0oOoo0OOOOOoo
#   25: OoO
#   26: o00ooo0Oooo
#   27: oOOOO0OO00
#   28: i1iI1
#   29: OoOOo0oO000oOo0
#   30: O0o
#   31: Oo0O0O

 85:           0 LOAD_CONST           (False)
               2 STORE_FAST           (i11iIii)

 86:           4 LOAD_CONST           (False)
               6 STORE_FAST           (OO)

 87:           8 LOAD_CONST           (None)
              10 STORE_FAST           (iiI1I11iiiiI)

 88:          12 LOAD_CONST           (None)
              14 STORE_FAST           (iII11iIi1iIiI)

 90:          16 LOAD_GLOBAL          (xbmcvfs)
              18 LOAD_METHOD          (exists)
              20 LOAD_CONST           ("special://home/addons/plugin.video.palantir3/moria.cm3")
              22 CALL_METHOD          (1 positional argument)
              24 EXTENDED_ARG         (1280)
              26 POP_JUMP_IF_TRUE     (to 1338)

 91:          28 SETUP_FINALLY        (to 136)

 92:          30 LOAD_GLOBAL          (getNameTempFile)
              32 CALL_FUNCTION        (0 positional arguments)
              34 STORE_FAST           (i1IIiII11)

 93:          36 LOAD_GLOBAL          (get_setting)
              38 LOAD_CONST           ("PalCO")
              40 CALL_FUNCTION        (1 positional argument)
              42 STORE_FAST           (iII11iIi1iIiI)

 95:          44 LOAD_GLOBAL          (os)
              46 LOAD_ATTR            (path)
              48 LOAD_METHOD          (isfile)
              50 LOAD_FAST            (i1IIiII11)
              52 CALL_METHOD          (1 positional argument)
              54 POP_JUMP_IF_FALSE    (to 72)
              56 LOAD_GLOBAL          (os)
              58 LOAD_ATTR            (path)
              60 LOAD_METHOD          (getsize)
              62 LOAD_FAST            (i1IIiII11)
              64 CALL_METHOD          (1 positional argument)
              66 LOAD_CONST           (10)
              68 COMPARE_OP           (<)
              70 POP_JUMP_IF_FALSE    (to 92)

 96:     >>   72 LOAD_FAST            (iII11iIi1iIiI)
              74 POP_JUMP_IF_TRUE     (to 80)

 96:          76 LOAD_CONST           (True)
              78 STORE_FAST           (i11iIii)

 97:     >>   80 LOAD_GLOBAL          (get_moria)
              82 CALL_FUNCTION        (0 positional arguments)
              84 POP_TOP

 98:          86 LOAD_CONST           (True)
              88 STORE_FAST           (OO)
              90 JUMP_FORWARD         (to 132)

101:     >>   92 LOAD_GLOBAL          (getDateUpdate)
              94 CALL_FUNCTION        (0 positional arguments)
              96 LOAD_CONST           ("last_up")
              98 BINARY_SUBSCR
             100 STORE_FAST           (IiIi1Ii1111)

102:         102 LOAD_FAST            (iII11iIi1iIiI)
             104 POP_JUMP_IF_FALSE    (to 122)
             106 LOAD_FAST            (IiIi1Ii1111)
             108 LOAD_FAST            (iII11iIi1iIiI)
             110 LOAD_CONST           (None)
             112 LOAD_CONST           (19)
             114 BUILD_SLICE          2
             116 BINARY_SUBSCR
             118 COMPARE_OP           (>)
             120 POP_JUMP_IF_FALSE    (to 132)

104:     >>  122 LOAD_GLOBAL          (get_moria)
             124 CALL_FUNCTION        (0 positional arguments)
             126 POP_TOP

105:         128 LOAD_CONST           (True)
             130 STORE_FAST           (OO)

106:     >>  132 POP_BLOCK
             134 JUMP_FORWARD         (to 328)

107:     >>  136 DUP_TOP
             138 LOAD_GLOBAL          (Exception)
             140 COMPARE_OP           (exception-match)
             142 EXTENDED_ARG         (256)
             144 POP_JUMP_IF_FALSE    (to 326)
             146 POP_TOP
             148 STORE_FAST           (o00)
             150 POP_TOP
             152 SETUP_FINALLY        (to 314)

108:         154 LOAD_GLOBAL          (str)
             156 LOAD_FAST            (o00)
             158 CALL_FUNCTION        (1 positional argument)
             160 LOAD_METHOD          (split)
             162 LOAD_CONST           ("|")
             164 CALL_METHOD          (1 positional argument)
             166 STORE_FAST           (i1I11i11)

109:         168 LOAD_FAST            (i1I11i11)
             170 LOAD_CONST           ("|")
             172 BINARY_SUBSCR
             174 STORE_FAST           (OoOOoO000O)

110:         176 LOAD_CONST           ("update")
             178 STORE_FAST           (O0o0O0o0o)

111:         180 LOAD_GLOBAL          (len)
             182 LOAD_FAST            (i1I11i11)
             184 CALL_FUNCTION        (1 positional argument)
             186 LOAD_CONST           (1)
             188 COMPARE_OP           (>)
             190 POP_JUMP_IF_FALSE    (to 200)

112:         192 LOAD_FAST            (i1I11i11)
             194 LOAD_CONST           (1)
             196 BINARY_SUBSCR
             198 STORE_FAST           (O0o0O0o0o)

114:     >>  200 LOAD_CONST           ("403")
             202 LOAD_FAST            (OoOOoO000O)
             204 COMPARE_OP           (in)
             206 POP_JUMP_IF_FALSE    (to 222)

115:         208 LOAD_FAST            (OoOOoO000O)
             210 LOAD_METHOD          (split)
             212 LOAD_CONST           ("for url")
             214 CALL_METHOD          (1 positional argument)
             216 LOAD_CONST           ("|")
             218 BINARY_SUBSCR
             220 STORE_FAST           (OoOOoO000O)

117:     >>  222 LOAD_GLOBAL          (xbmcgui)
             224 LOAD_ATTR            (NOTIFICATION_ERROR)
             226 STORE_FAST           (oO00o00OO)

118:         228 LOAD_GLOBAL          (xbmcgui)
             230 LOAD_METHOD          (Dialog)
             232 CALL_METHOD          (0 positional arguments)
             234 LOAD_METHOD          (notification)
             236 LOAD_GLOBAL          (o00o)
             238 LOAD_FAST            (OoOOoO000O)
             240 LOAD_FAST            (oO00o00OO)
             242 LOAD_CONST           (3000)
             244 CALL_METHOD          (4 positional arguments)
             246 POP_TOP

119:         248 LOAD_GLOBAL          (logger)
             250 LOAD_CONST           ("%s: %s")
             252 LOAD_FAST            (O0o0O0o0o)
             254 LOAD_FAST            (OoOOoO000O)
             256 BUILD_TUPLE          2
             258 BINARY_MODULO
             260 LOAD_CONST           ("error")
             262 CALL_FUNCTION        (2 positional arguments)
             264 POP_TOP

121:         266 LOAD_GLOBAL          (os)
             268 LOAD_ATTR            (path)
             270 LOAD_METHOD          (isfile)
             272 LOAD_GLOBAL          (getNameTempFile)
             274 CALL_FUNCTION        (0 positional arguments)
             276 CALL_METHOD          (1 positional argument)
             278 EXTENDED_ARG         (256)
             280 POP_JUMP_IF_FALSE    (to 292)
             282 LOAD_FAST            (O0o0O0o0o)
             284 LOAD_CONST           (('getDateUpdate', 'executeSelect'))
             286 COMPARE_OP           (in)
             288 EXTENDED_ARG         (256)
             290 POP_JUMP_IF_FALSE    (to 310)

123:     >>  292 LOAD_GLOBAL          (logger)
             294 LOAD_CONST           ("No existe la base")
             296 CALL_FUNCTION        (1 positional argument)
             298 POP_TOP

124:         300 POP_BLOCK
             302 POP_EXCEPT
             304 CALL_FINALLY         (to 314)
             306 LOAD_CONST           (None)
             308 RETURN_VALUE

125:     >>  310 POP_BLOCK
             312 BEGIN_FINALLY
         >>  314 LOAD_CONST           (None)
             316 STORE_FAST           (o00)
             318 DELETE_FAST          (o00)
             320 END_FINALLY
             322 POP_EXCEPT
             324 JUMP_FORWARD         (to 328)
         >>  326 END_FINALLY

126:     >>  328 LOAD_GLOBAL          (MoriaDB)
             330 CALL_FUNCTION        (0 positional arguments)
             332 EXTENDED_ARG         (768)
             334 SETUP_WITH           (to 1330)
             336 STORE_FAST           (OOo0OOOo0O)

127:         338 SETUP_FINALLY        (to 368)

128:         340 LOAD_FAST            (OOo0OOOo0O)
             342 LOAD_METHOD          (executeSelect)

130:         344 LOAD_CONST           ("SELECT version, mensaje_inicial, mensaje_update, notificacion_update, video_intro from version ORDER by version DESC")

128:         346 CALL_METHOD          (1 positional argument)

130:         348 LOAD_CONST           ("|")

128:         350 BINARY_SUBSCR
             352 UNPACK_SEQUENCE      5
             354 STORE_FAST           (oOo0Oo)
             356 STORE_FAST           (O0ooooO)
             358 STORE_FAST           (iII)
             360 STORE_FAST           (OooOO00o)
             362 STORE_FAST           (OOO00000oO)
             364 POP_BLOCK
             366 JUMP_FORWARD         (to 400)

131:     >>  368 POP_TOP
             370 POP_TOP
             372 POP_TOP

132:         374 LOAD_GLOBAL          (logger)
             376 LOAD_CONST           ("No existe la base")
             378 CALL_FUNCTION        (1 positional argument)
             380 POP_TOP

133:         382 POP_EXCEPT
             384 POP_BLOCK
             386 BEGIN_FINALLY
             388 WITH_CLEANUP_START
             390 WITH_CLEANUP_FINISH
             392 POP_FINALLY          0
             394 LOAD_CONST           (None)
             396 RETURN_VALUE
             398 END_FINALLY

134:     >>  400 LOAD_GLOBAL          (Watched)
             402 CALL_FUNCTION        (0 positional arguments)
             404 EXTENDED_ARG         (768)
             406 SETUP_WITH           (to 1320)
             408 STORE_FAST           (I11I1iI)

135:         410 LOAD_FAST            (OO)
             412 EXTENDED_ARG         (512)
             414 POP_JUMP_IF_FALSE    (to 596)

137:         416 LOAD_GLOBAL          (CACHE)
             418 LOAD_METHOD          (clear)
             420 LOAD_CONST           ("all")
             422 CALL_METHOD          (1 positional argument)
             424 POP_TOP

139:         426 LOAD_FAST            (I11I1iI)
             428 LOAD_METHOD          (setShowUpdated)
             430 CALL_METHOD          (0 positional arguments)
             432 POP_TOP

141:         434 LOAD_GLOBAL          (len)
             436 LOAD_FAST            (OOo0OOOo0O)
             438 LOAD_METHOD          (executeSelect)
             440 LOAD_CONST           ("select tmdb FROM enlaces_series group by tmdb,temporada,episodio;")
             442 CALL_METHOD          (1 positional argument)
             444 CALL_FUNCTION        (1 positional argument)
             446 STORE_FAST           (OOoOo00o)

142:         448 LOAD_GLOBAL          (len)
             450 LOAD_FAST            (OOo0OOOo0O)
             452 LOAD_METHOD          (executeSelect)
             454 LOAD_CONST           ("select * FROM pelis")
             456 CALL_METHOD          (1 positional argument)
             458 CALL_FUNCTION        (1 positional argument)
             460 STORE_FAST           (oo0ooooo0ooo)

144:         462 LOAD_FAST            (OooOO00o)
             464 EXTENDED_ARG         (256)
             466 POP_JUMP_IF_FALSE    (to 486)

145:         468 LOAD_GLOBAL          (re)
             470 LOAD_METHOD          (sub)
             472 LOAD_CONST           ("\\\\n")
             474 LOAD_GLOBAL          (os)
             476 LOAD_ATTR            (linesep)
             478 LOAD_FAST            (OooOO00o)
             480 CALL_METHOD          (3 positional arguments)
             482 STORE_FAST           (I1iO0oo000o)
             484 JUMP_FORWARD         (to 506)

147:     >>  486 LOAD_GLOBAL          (localize)
             488 LOAD_CONST           (30052)
             490 CALL_FUNCTION        (1 positional argument)
             492 LOAD_FAST            (oOo0Oo)
             494 LOAD_FAST            (OOoOo00o)
             496 LOAD_FAST            (oo0ooooo0ooo)
             498 BINARY_ADD
             500 BUILD_TUPLE          2
             502 BINARY_MODULO
             504 STORE_FAST           (I1iO0oo000o)

149:     >>  506 LOAD_FAST            (I1iO0oo000o)
             508 EXTENDED_ARG         (512)
             510 POP_JUMP_IF_FALSE    (to 534)

150:         512 LOAD_GLOBAL          (xbmcgui)
             514 LOAD_METHOD          (Dialog)
             516 CALL_METHOD          (0 positional arguments)
             518 LOAD_METHOD          (notification)
             520 LOAD_GLOBAL          (o00o)
             522 LOAD_FAST            (I1iO0oo000o)
             524 LOAD_GLOBAL          (xbmcgui)
             526 LOAD_ATTR            (NOTIFICATION_INFO)
             528 LOAD_CONST           (5000)
             530 CALL_METHOD          (4 positional arguments)
             532 POP_TOP

152:     >>  534 LOAD_FAST            (i11iIii)
             536 EXTENDED_ARG         (512)
             538 POP_JUMP_IF_FALSE    (to 558)

153:         540 LOAD_GLOBAL          (re)
             542 LOAD_METHOD          (sub)
             544 LOAD_CONST           ("\\\\n")
             546 LOAD_GLOBAL          (os)
             548 LOAD_ATTR            (linesep)
             550 LOAD_FAST            (O0ooooO)
             552 CALL_METHOD          (3 positional arguments)
             554 STORE_FAST           (iiI1I11iiiiI)
             556 JUMP_FORWARD         (to 580)

154:     >>  558 LOAD_FAST            (iII)
             560 EXTENDED_ARG         (512)
             562 POP_JUMP_IF_FALSE    (to 580)

155:         564 LOAD_GLOBAL          (re)
             566 LOAD_METHOD          (sub)
             568 LOAD_CONST           ("\\\\n")
             570 LOAD_GLOBAL          (os)
             572 LOAD_ATTR            (linesep)
             574 LOAD_FAST            (iII)
             576 CALL_METHOD          (3 positional arguments)
             578 STORE_FAST           (iiI1I11iiiiI)

157:     >>  580 LOAD_FAST            (iiI1I11iiiiI)
             582 EXTENDED_ARG         (512)
             584 POP_JUMP_IF_FALSE    (to 596)

158:         586 LOAD_GLOBAL          (DialogImage)
             588 LOAD_GLOBAL          (o00o)
             590 LOAD_FAST            (iiI1I11iiiiI)
             592 CALL_FUNCTION        (2 positional arguments)
             594 POP_TOP

160:     >>  596 LOAD_GLOBAL          (ISESTUARYPALANTIR)
             598 EXTENDED_ARG         (1280)
             600 POP_JUMP_IF_FALSE    (to 1316)

162:         602 LOAD_FAST            (I11I1iI)
             604 LOAD_METHOD          (actualizarWidgetFavoritos)
             606 CALL_METHOD          (0 positional arguments)
             608 POP_TOP

165:         610 LOAD_CONST           (('p3especialesname', 'p3especialespath', 'p3especiales2name', 'p3especiales2path'))
             612 GET_ITER
         >>  614 FOR_ITER             (to 632)
             616 STORE_FAST           (oOo)

166:         618 LOAD_GLOBAL          (WINDOW)
             620 LOAD_METHOD          (clearProperty)
             622 LOAD_FAST            (oOo)
             624 CALL_METHOD          (1 positional argument)
             626 POP_TOP

167:         628 EXTENDED_ARG         (512)
             630 JUMP_ABSOLUTE        (to 614)

168:     >>  632 LOAD_GLOBAL          (list)
             634 CALL_FUNCTION        (0 positional arguments)
             636 STORE_FAST           (OOOOOoo0oOo00)

169:         638 LOAD_FAST            (OOo0OOOo0O)
             640 LOAD_METHOD          (executeSelect)

170:         642 LOAD_CONST           ('SELECT label,action,sql from menus where sql like "%where coleccion like%" and menu_id > 0 and menu_id <= 100')

169:         644 CALL_METHOD          (1 positional argument)
             646 STORE_FAST           (OOOOOoo0oOo00)

171:         648 LOAD_FAST            (OOOOOoo0oOo00)
             650 LOAD_METHOD          (extend)
             652 LOAD_FAST            (OOo0OOOo0O)
             654 LOAD_METHOD          (executeSelect)

172:         656 LOAD_CONST           ('SELECT label,action,sql from menus where action = "listado_trakt" and menu_id > 0 and menu_id <= 100')

171:         658 CALL_METHOD          (1 positional argument)
             660 CALL_METHOD          (1 positional argument)
             662 POP_TOP

174:         664 LOAD_FAST            (OOOOOoo0oOo00)
             666 EXTENDED_ARG         (1024)
             668 POP_JUMP_IF_FALSE    (to 1204)

175:         670 LOAD_GLOBAL          (list)
             672 CALL_FUNCTION        (0 positional arguments)
             674 STORE_FAST           (ooOo00o)

176:         676 LOAD_GLOBAL          (list)
             678 CALL_FUNCTION        (0 positional arguments)
             680 STORE_FAST           (o0oOoo0OOOOOoo)

177:         682 LOAD_GLOBAL          (list)
             684 CALL_FUNCTION        (0 positional arguments)
             686 STORE_FAST           (OoO)

178:         688 LOAD_FAST            (OOOOOoo0oOo00)
             690 GET_ITER
         >>  692 FOR_ITER             (to 822)
             694 UNPACK_SEQUENCE      3
             696 STORE_FAST           (o00ooo0Oooo)
             698 STORE_FAST           (oOOOO0OO00)
             700 STORE_FAST           (i1iI1)

179:         702 LOAD_CONST           ("v_pelis")
             704 LOAD_FAST            (i1iI1)
             706 COMPARE_OP           (in)
             708 EXTENDED_ARG         (512)
             710 POP_JUMP_IF_FALSE    (to 744)
             712 LOAD_GLOBAL          (len)
             714 LOAD_FAST            (ooOo00o)
             716 CALL_FUNCTION        (1 positional argument)
             718 LOAD_CONST           (2)
             720 COMPARE_OP           (<)
             722 EXTENDED_ARG         (512)
             724 POP_JUMP_IF_FALSE    (to 744)

180:         726 LOAD_FAST            (ooOo00o)
             728 LOAD_METHOD          (append)
             730 LOAD_FAST            (o00ooo0Oooo)
             732 LOAD_FAST            (oOOOO0OO00)
             734 LOAD_FAST            (i1iI1)
             736 BUILD_TUPLE          3
             738 CALL_METHOD          (1 positional argument)
             740 POP_TOP
             742 JUMP_FORWARD         (to 784)

181:     >>  744 LOAD_CONST           ("v_series")
             746 LOAD_FAST            (i1iI1)
             748 COMPARE_OP           (in)
             750 EXTENDED_ARG         (768)
             752 POP_JUMP_IF_FALSE    (to 784)
             754 LOAD_GLOBAL          (len)
             756 LOAD_FAST            (o0oOoo0OOOOOoo)
             758 CALL_FUNCTION        (1 positional argument)
             760 LOAD_CONST           (2)
             762 COMPARE_OP           (<)
             764 EXTENDED_ARG         (768)
             766 POP_JUMP_IF_FALSE    (to 784)

182:         768 LOAD_FAST            (o0oOoo0OOOOOoo)
             770 LOAD_METHOD          (append)
             772 LOAD_FAST            (o00ooo0Oooo)
             774 LOAD_FAST            (oOOOO0OO00)
             776 LOAD_FAST            (i1iI1)
             778 BUILD_TUPLE          3
             780 CALL_METHOD          (1 positional argument)
             782 POP_TOP

184:     >>  784 LOAD_GLOBAL          (len)
             786 LOAD_FAST            (ooOo00o)
             788 CALL_FUNCTION        (1 positional argument)
             790 LOAD_CONST           (1)
             792 COMPARE_OP           (>=)
             794 EXTENDED_ARG         (512)
             796 POP_JUMP_IF_FALSE    (to 692)
             798 LOAD_GLOBAL          (len)
             800 LOAD_FAST            (o0oOoo0OOOOOoo)
             802 CALL_FUNCTION        (1 positional argument)
             804 LOAD_CONST           (1)
             806 COMPARE_OP           (>=)
             808 EXTENDED_ARG         (512)
             810 POP_JUMP_IF_FALSE    (to 692)

185:         812 POP_TOP
             814 EXTENDED_ARG         (768)
             816 JUMP_ABSOLUTE        (to 822)

186:         818 EXTENDED_ARG         (512)
             820 JUMP_ABSOLUTE        (to 692)

187:     >>  822 LOAD_FAST            (ooOo00o)
             824 EXTENDED_ARG         (768)
             826 POP_JUMP_IF_FALSE    (to 954)
             828 LOAD_FAST            (o0oOoo0OOOOOoo)
             830 EXTENDED_ARG         (768)
             832 POP_JUMP_IF_FALSE    (to 954)

188:         834 LOAD_FAST            (OOOOOoo0oOo00)
             836 GET_ITER
         >>  838 FOR_ITER             (to 952)
             840 STORE_FAST           (OoOOo0oO000oOo0)

189:         842 LOAD_FAST            (OoOOo0oO000oOo0)
             844 LOAD_FAST            (ooOo00o)
             846 LOAD_CONST           ("|")
             848 BINARY_SUBSCR
             850 COMPARE_OP           (==)
             852 EXTENDED_ARG         (768)
             854 POP_JUMP_IF_FALSE    (to 886)
             856 LOAD_FAST            (ooOo00o)
             858 LOAD_CONST           ("|")
             860 BINARY_SUBSCR
             862 LOAD_FAST            (OoO)
             864 COMPARE_OP           (not-in)
             866 EXTENDED_ARG         (768)
             868 POP_JUMP_IF_FALSE    (to 886)

190:         870 LOAD_FAST            (OoO)
             872 LOAD_METHOD          (append)
             874 LOAD_FAST            (ooOo00o)
             876 LOAD_CONST           ("|")
             878 BINARY_SUBSCR
             880 CALL_METHOD          (1 positional argument)
             882 POP_TOP
             884 JUMP_FORWARD         (to 928)

191:     >>  886 LOAD_FAST            (OoOOo0oO000oOo0)
             888 LOAD_FAST            (o0oOoo0OOOOOoo)
             890 LOAD_CONST           ("|")
             892 BINARY_SUBSCR
             894 COMPARE_OP           (==)
             896 EXTENDED_ARG         (768)
             898 POP_JUMP_IF_FALSE    (to 928)
             900 LOAD_FAST            (o0oOoo0OOOOOoo)
             902 LOAD_CONST           ("|")
             904 BINARY_SUBSCR
             906 LOAD_FAST            (OoO)
             908 COMPARE_OP           (not-in)
             910 EXTENDED_ARG         (768)
             912 POP_JUMP_IF_FALSE    (to 928)

192:         914 LOAD_FAST            (OoO)
             916 LOAD_METHOD          (append)
             918 LOAD_FAST            (o0oOoo0OOOOOoo)
             920 LOAD_CONST           ("|")
             922 BINARY_SUBSCR
             924 CALL_METHOD          (1 positional argument)
             926 POP_TOP

193:     >>  928 LOAD_GLOBAL          (len)
             930 LOAD_FAST            (OoO)
             932 CALL_FUNCTION        (1 positional argument)
             934 LOAD_CONST           (2)
             936 COMPARE_OP           (==)
             938 EXTENDED_ARG         (768)
             940 POP_JUMP_IF_FALSE    (to 838)

194:         942 POP_TOP
             944 EXTENDED_ARG         (1024)
             946 JUMP_ABSOLUTE        (to 1032)
             948 EXTENDED_ARG         (768)
             950 JUMP_ABSOLUTE        (to 838)
         >>  952 JUMP_FORWARD         (to 1032)

195:     >>  954 LOAD_GLOBAL          (len)
             956 LOAD_FAST            (ooOo00o)
             958 CALL_FUNCTION        (1 positional argument)
             960 LOAD_CONST           (2)
             962 COMPARE_OP           (>=)
             964 EXTENDED_ARG         (768)
             966 POP_JUMP_IF_FALSE    (to 982)

196:         968 LOAD_FAST            (ooOo00o)
             970 LOAD_CONST           (None)
             972 LOAD_CONST           (2)
             974 BUILD_SLICE          2
             976 BINARY_SUBSCR
             978 STORE_FAST           (OoO)
             980 JUMP_FORWARD         (to 1032)

197:     >>  982 LOAD_GLOBAL          (len)
             984 LOAD_FAST            (o0oOoo0OOOOOoo)
             986 CALL_FUNCTION        (1 positional argument)
             988 LOAD_CONST           (2)
             990 COMPARE_OP           (>=)
             992 EXTENDED_ARG         (768)
             994 POP_JUMP_IF_FALSE    (to 1010)

198:         996 LOAD_FAST            (o0oOoo0OOOOOoo)
             998 LOAD_CONST           (None)
            1000 LOAD_CONST           (2)
            1002 BUILD_SLICE          2
            1004 BINARY_SUBSCR
            1006 STORE_FAST           (OoO)
            1008 JUMP_FORWARD         (to 1032)

199:     >> 1010 LOAD_FAST            (ooOo00o)
            1012 EXTENDED_ARG         (768)
            1014 POP_JUMP_IF_FALSE    (to 1022)

200:        1016 LOAD_FAST            (ooOo00o)
            1018 STORE_FAST           (OoO)
            1020 JUMP_FORWARD         (to 1032)

201:     >> 1022 LOAD_FAST            (o0oOoo0OOOOOoo)
            1024 EXTENDED_ARG         (1024)
            1026 POP_JUMP_IF_FALSE    (to 1032)

202:        1028 LOAD_FAST            (o0oOoo0OOOOOoo)
            1030 STORE_FAST           (OoO)

204:     >> 1032 LOAD_FAST            (OoO)
            1034 EXTENDED_ARG         (1024)
            1036 POP_JUMP_IF_FALSE    (to 1114)

205:        1038 LOAD_FAST            (OoO)
            1040 LOAD_CONST           ("|")
            1042 BINARY_SUBSCR
            1044 UNPACK_SEQUENCE      3
            1046 STORE_FAST           (o00ooo0Oooo)
            1048 STORE_FAST           (oOOOO0OO00)
            1050 STORE_FAST           (i1iI1)

206:        1052 LOAD_GLOBAL          (WINDOW)
            1054 LOAD_METHOD          (setProperty)
            1056 LOAD_CONST           ("p3especialesname")
            1058 LOAD_FAST            (o00ooo0Oooo)
            1060 CALL_METHOD          (2 positional arguments)
            1062 POP_TOP

207:        1064 LOAD_GLOBAL          (WINDOW)
            1066 LOAD_METHOD          (setProperty)
            1068 LOAD_CONST           ("p3especialespath")
            1070 LOAD_CONST           ("plugin://plugin.video.palantir3/?")

208:        1072 LOAD_GLOBAL          (P3Item)
            1074 LOAD_FAST            (o00ooo0Oooo)
            1076 LOAD_FAST            (oOOOO0OO00)
            1078 LOAD_FAST            (i1iI1)
            1080 LOAD_CONST           (True)
            1082 LOAD_CONST           ("WidgetEspeciales")

209:        1084 LOAD_CONST           ("v_pelis")
            1086 LOAD_FAST            (i1iI1)
            1088 COMPARE_OP           (in)
            1090 EXTENDED_ARG         (1024)
            1092 POP_JUMP_IF_FALSE    (to 1098)
            1094 LOAD_CONST           ("movies")
            1096 JUMP_FORWARD         (to 1100)
         >> 1098 LOAD_CONST           ("tvshows")

208:     >> 1100 LOAD_CONST           (('label', 'action', 'sql', 'isWidget', 'nameWidget', 'content'))
            1102 CALL_FUNCTION_KW     (6 total positional and keyword args)
            1104 LOAD_METHOD          (tourl)
            1106 CALL_METHOD          (0 positional arguments)

207:        1108 BINARY_ADD
            1110 CALL_METHOD          (2 positional arguments)
            1112 POP_TOP

210:     >> 1114 LOAD_GLOBAL          (len)
            1116 LOAD_FAST            (OoO)
            1118 CALL_FUNCTION        (1 positional argument)
            1120 LOAD_CONST           (1)
            1122 COMPARE_OP           (>)
            1124 EXTENDED_ARG         (1024)
            1126 POP_JUMP_IF_FALSE    (to 1204)

211:        1128 LOAD_FAST            (OoO)
            1130 LOAD_CONST           (1)
            1132 BINARY_SUBSCR
            1134 UNPACK_SEQUENCE      3
            1136 STORE_FAST           (o00ooo0Oooo)
            1138 STORE_FAST           (oOOOO0OO00)
            1140 STORE_FAST           (i1iI1)

212:        1142 LOAD_GLOBAL          (WINDOW)
            1144 LOAD_METHOD          (setProperty)
            1146 LOAD_CONST           ("p3especiales2name")
            1148 LOAD_FAST            (o00ooo0Oooo)
            1150 CALL_METHOD          (2 positional arguments)
            1152 POP_TOP

213:        1154 LOAD_GLOBAL          (WINDOW)
            1156 LOAD_METHOD          (setProperty)
            1158 LOAD_CONST           ("p3especiales2path")
            1160 LOAD_CONST           ("plugin://plugin.video.palantir3/?")

214:        1162 LOAD_GLOBAL          (P3Item)
            1164 LOAD_FAST            (o00ooo0Oooo)
            1166 LOAD_FAST            (oOOOO0OO00)
            1168 LOAD_FAST            (i1iI1)
            1170 LOAD_CONST           (True)

215:        1172 LOAD_CONST           ("WidgetEspeciales2")

216:        1174 LOAD_CONST           ("v_pelis")
            1176 LOAD_FAST            (i1iI1)
            1178 COMPARE_OP           (in)
            1180 EXTENDED_ARG         (1024)
            1182 POP_JUMP_IF_FALSE    (to 1188)
            1184 LOAD_CONST           ("movies")
            1186 JUMP_FORWARD         (to 1190)
         >> 1188 LOAD_CONST           ("tvshows")

214:     >> 1190 LOAD_CONST           (('label', 'action', 'sql', 'isWidget', 'nameWidget', 'content'))
            1192 CALL_FUNCTION_KW     (6 total positional and keyword args)
            1194 LOAD_METHOD          (tourl)
            1196 CALL_METHOD          (0 positional arguments)

213:        1198 BINARY_ADD
            1200 CALL_METHOD          (2 positional arguments)
            1202 POP_TOP

219:     >> 1204 LOAD_GLOBAL          (xbmcvfs)
            1206 LOAD_METHOD          (translatePath)
            1208 LOAD_CONST           ("special://profile/addon_data/skin.estuary.palantir/video_especial.mp4")
            1210 CALL_METHOD          (1 positional argument)
            1212 STORE_FAST           (O0o)

220:        1214 LOAD_FAST            (OOO00000oO)
            1216 EXTENDED_ARG         (1024)
            1218 POP_JUMP_IF_TRUE     (to 1256)

222:        1220 LOAD_GLOBAL          (os)
            1222 LOAD_ATTR            (path)
            1224 LOAD_METHOD          (exists)
            1226 LOAD_FAST            (O0o)
            1228 CALL_METHOD          (1 positional argument)
            1230 EXTENDED_ARG         (1024)
            1232 POP_JUMP_IF_FALSE    (to 1244)

223:        1234 LOAD_GLOBAL          (os)
            1236 LOAD_METHOD          (remove)
            1238 LOAD_FAST            (O0o)
            1240 CALL_METHOD          (1 positional argument)
            1242 POP_TOP

224:     >> 1244 LOAD_GLOBAL          (set_setting)
            1246 LOAD_CONST           ("video_intro")
            1248 LOAD_CONST           ("")
            1250 CALL_FUNCTION        (2 positional arguments)
            1252 POP_TOP
            1254 JUMP_FORWARD         (to 1316)

225:     >> 1256 LOAD_FAST            (OOO00000oO)
            1258 LOAD_GLOBAL          (get_setting)
            1260 LOAD_CONST           ("video_intro")
            1262 LOAD_CONST           ("")
            1264 CALL_FUNCTION        (2 positional arguments)
            1266 COMPARE_OP           (!=)
            1268 EXTENDED_ARG         (1280)
            1270 POP_JUMP_IF_TRUE     (to 1286)
            1272 LOAD_GLOBAL          (os)
            1274 LOAD_ATTR            (path)
            1276 LOAD_METHOD          (exists)
            1278 LOAD_FAST            (O0o)
            1280 CALL_METHOD          (1 positional argument)
            1282 EXTENDED_ARG         (1280)
            1284 POP_JUMP_IF_TRUE     (to 1316)

227:     >> 1286 LOAD_GLOBAL          (Thread)
            1288 LOAD_GLOBAL          (I1ii1111IIi)
            1290 LOAD_FAST            (OOO00000oO)
            1292 LOAD_FAST            (O0o)
            1294 BUILD_LIST           2
            1296 LOAD_CONST           (('target', 'args'))
            1298 CALL_FUNCTION_KW     (2 total positional and keyword args)
            1300 STORE_FAST           (Oo0O0O)

228:        1302 LOAD_CONST           (True)
            1304 LOAD_FAST            (Oo0O0O)
            1306 STORE_ATTR           (daemon)

229:        1308 LOAD_FAST            (Oo0O0O)
            1310 LOAD_METHOD          (start)
            1312 CALL_METHOD          (0 positional arguments)
            1314 POP_TOP
         >> 1316 POP_BLOCK
            1318 BEGIN_FINALLY
         >> 1320 WITH_CLEANUP_START
            1322 WITH_CLEANUP_FINISH
            1324 END_FINALLY
            1326 POP_BLOCK
            1328 BEGIN_FINALLY
         >> 1330 WITH_CLEANUP_START
            1332 WITH_CLEANUP_FINISH
            1334 END_FINALLY
            1336 JUMP_FORWARD         (to 1346)

231:     >> 1338 LOAD_GLOBAL          (logger)
            1340 LOAD_CONST           ("BBDD moria.cm3")
            1342 CALL_FUNCTION        (1 positional argument)
            1344 POP_TOP

233:     >> 1346 LOAD_CONST           (None)
            1348 RETURN_VALUE


# Method Name:       IIiI1i
# Filename:          <string>
# Argument count:    1
# Position-only argument count: 0
# Keyword-only arguments: 0
# Number of locals:  15
# Stack size:        9
# Flags:             0x00000003 (NEWLOCALS | OPTIMIZED)
# First Line:        234
# Constants:
#    0: None
#    1: 'menu'
#    2: ('play_mis_serieS', 'selectvideos_', 'play_nextEpisode')
#    3: True
#    4: False
#    5: 'WidgetRandom'
#    6: <Code38 code object <lambda> at 0x1624b8a3210, file <string>>, line 254
#    7: 'IIiI1i.<locals>.<lambda>'
#    8: ('target',)
#    9: 'libs.ioiI1iIiiIi'
#   10: ('fromlist',)
#   11: ','
#   12: <Code38 code object <listcomp> at 0x1624c5b3790, file <string>>, line 265
#   13: 'IIiI1i.<locals>.<listcomp>'
#   14: 3
#   15: ('days',)
#   16: ('pickle_data', 'sub_categoria', 'expiration', 'inWidget')
#   17: '<listcomp>'
#   18: ''
#   19: (50, 51, 55)
#   20: ']([^\\[]+)'
#   21: ' '
#   22: '\\\\n|\\\\r|\\\\t|\\\\s{2}|&nbsp;'
#   23: '%s?%s'
#   24: 1
#   25: '\\[[^\\]]*]'
#   26: '[COLOR Ffd414fc]Palantir 3[/COLOR] - '
#   27: '\\s+'
#   28: '[COLOR Ffd414fc]Palantir 3[/COLOR]'
#   29: 'breadcrumbs_label'
#   30: ('handle', 'key', 'value')
#   31: ('handle', 'sortMethod')
#   32: ('handle', 'succeeded', 'cacheToDisc')
#   33: 100
#   34: 'Container.SetViewMode(%s)'
# Names:
#    0: list
#    1: oOo0O00
#    2: ooOOO
#    3: IIiIIiIi11I1
#    4: OooOoo
#    5: I1I
#    6: OOO00000O
#    7: action
#    8: is_label
#    9: i1iiIII111
#   10: Iii1i
#   11: o0
#   12: iI1iII1I1I1i
#   13: Ii111
#   14: ooo000
#   15: isWidget
#   16: Oo
#   17: CACHE
#   18: get
#   19: nameWidget
#   20: Thread
#   21: daemon
#   22: start
#   23: i1i1i1111I
#   24: o0i1i
#   25: getattr
#   26: __import__
#   27: i1
#   28: Ooo0Ooo
#   29: join
#   30: datetime
#   31: timedelta
#   32: set
#   33: content
#   34: Watched
#   35: getView
#   36: label
#   37: I1Ii1I1
#   38: re
#   39: findall
#   40: startswith
#   41: sub
#   42: xbmcgui
#   43: ListItem
#   44: title
#   45: IiIIii11Ii
#   46: isPlayable
#   47: isinstance
#   48: isFolder
#   49: bool
#   50: setInfoTag
#   51: append
#   52: sys
#   53: argv
#   54: tourl
#   55: xbmcplugin
#   56: addDirectoryItems
#   57: int
#   58: len
#   59: strip
#   60: setProperty
#   61: addSortMethod
#   62: SORT_METHOD_NONE
#   63: setContent
#   64: endOfDirectory
#   65: ISESTUARYPALANTIR
#   66: xbmc
#   67: sleep
#   68: executebuiltin
#   69: Ii
# Varnames:
#	p3Item, OoOOooO0oOO0Oo, iiI1i1IiiiIi1, Oo0o0Oo, oOO, ii1IiiIiI, Ooo0O00o, O0ooOO0O0O0O, I11I1iI, OOOoo, Ii1Ii1, I111i1i11iII, i11I1IiIiI1i, ii11I1i1i, o0OOo0OoO
# Positional arguments:
#	p3Item
# Local variables:
#    1: OoOOooO0oOO0Oo
#    2: iiI1i1IiiiIi1
#    3: Oo0o0Oo
#    4: oOO
#    5: ii1IiiIiI
#    6: Ooo0O00o
#    7: O0ooOO0O0O0O
#    8: I11I1iI
#    9: OOOoo
#   10: Ii1Ii1
#   11: I111i1i11iII
#   12: i11I1IiIiI1i
#   13: ii11I1i1i
#   14: o0OOo0OoO
# Free variables:
#    0: p3Item

235:           0 LOAD_GLOBAL          (list)
               2 CALL_FUNCTION        (0 positional arguments)
               4 STORE_FAST           (OoOOooO0oOO0Oo)

236:           6 LOAD_GLOBAL          (list)
               8 CALL_FUNCTION        (0 positional arguments)
              10 STORE_FAST           (iiI1i1IiiiIi1)

239:          12 LOAD_DEREF           (p3Item)
              14 LOAD_ATTR            (action)
              16 POP_JUMP_IF_TRUE     (to 36)

240:          18 LOAD_DEREF           (p3Item)
              20 LOAD_METHOD          (is_label)
              22 CALL_METHOD          (0 positional arguments)
              24 POP_JUMP_IF_FALSE    (to 30)

242:          26 LOAD_CONST           (None)
              28 RETURN_VALUE

244:     >>   30 LOAD_CONST           ("menu")
              32 LOAD_DEREF           (p3Item)
              34 STORE_ATTR           (action)

246:     >>   36 LOAD_DEREF           (p3Item)
              38 LOAD_ATTR            (action)
              40 LOAD_CONST           (('play_mis_serieS', 'selectvideos_', 'play_nextEpisode'))
              42 COMPARE_OP           (in)
              44 POP_JUMP_IF_FALSE    (to 50)
              46 LOAD_CONST           (True)
              48 JUMP_FORWARD         (to 52)
         >>   50 LOAD_CONST           (False)
         >>   52 STORE_FAST           (Oo0o0Oo)

248:          54 LOAD_DEREF           (p3Item)
              56 LOAD_ATTR            (isWidget)
              58 POP_JUMP_IF_FALSE    (to 136)

251:          60 SETUP_FINALLY        (to 124)

252:          62 LOAD_GLOBAL          (CACHE)
              64 LOAD_METHOD          (get)
              66 LOAD_DEREF           (p3Item)
              68 LOAD_ATTR            (nameWidget)
              70 CALL_METHOD          (1 positional argument)
              72 STORE_FAST           (OoOOooO0oOO0Oo)

253:          74 LOAD_FAST            (OoOOooO0oOO0Oo)
              76 POP_JUMP_IF_FALSE    (to 120)
              78 LOAD_DEREF           (p3Item)
              80 LOAD_ATTR            (nameWidget)
              82 LOAD_CONST           ("WidgetRandom")
              84 COMPARE_OP           (==)
              86 POP_JUMP_IF_FALSE    (to 120)

254:          88 LOAD_GLOBAL          (Thread)
              90 LOAD_CLOSURE         (p3Item)
              92 BUILD_TUPLE          1
              94 LOAD_CONST           (<Code38 code object <lambda> at 0x1624b8a3210, file <string>>, line 254)
              96 LOAD_CONST           ("IIiI1i.<locals>.<lambda>")
              98 MAKE_FUNCTION        (closure)
             100 LOAD_CONST           (('target',))
             102 CALL_FUNCTION_KW     (1 total positional and keyword args)
             104 STORE_FAST           (oOO)

255:         106 LOAD_CONST           (True)
             108 LOAD_FAST            (oOO)
             110 STORE_ATTR           (daemon)

256:         112 LOAD_FAST            (oOO)
             114 LOAD_METHOD          (start)
             116 CALL_METHOD          (0 positional arguments)
             118 POP_TOP
         >>  120 POP_BLOCK
             122 JUMP_FORWARD         (to 136)

257:     >>  124 POP_TOP
             126 POP_TOP
             128 POP_TOP

257:         130 POP_EXCEPT
             132 JUMP_FORWARD         (to 136)
             134 END_FINALLY

259:     >>  136 LOAD_FAST            (OoOOooO0oOO0Oo)
             138 POP_JUMP_IF_TRUE     (to 246)

261:         140 LOAD_GLOBAL          (getattr)
             142 LOAD_GLOBAL          (__import__)
             144 LOAD_CONST           ("libs.ioiI1iIiiIi")
             146 LOAD_DEREF           (p3Item)
             148 LOAD_ATTR            (action)
             150 BUILD_LIST           1
             152 LOAD_CONST           (('fromlist',))
             154 CALL_FUNCTION_KW     (2 total positional and keyword args)
             156 LOAD_DEREF           (p3Item)
             158 LOAD_ATTR            (action)
             160 CALL_FUNCTION        (2 positional arguments)
             162 LOAD_DEREF           (p3Item)
             164 CALL_FUNCTION        (1 positional argument)
             166 STORE_FAST           (OoOOooO0oOO0Oo)

263:         168 LOAD_DEREF           (p3Item)
             170 LOAD_ATTR            (isWidget)
             172 POP_JUMP_IF_FALSE    (to 246)
             174 LOAD_FAST            (OoOOooO0oOO0Oo)
             176 POP_JUMP_IF_FALSE    (to 246)
             178 LOAD_DEREF           (p3Item)
             180 LOAD_ATTR            (nameWidget)
             182 LOAD_CONST           ("WidgetRandom")
             184 COMPARE_OP           (!=)
             186 POP_JUMP_IF_FALSE    (to 246)

265:         188 LOAD_CONST           (",")
             190 LOAD_METHOD          (join)
             192 LOAD_CONST           (<Code38 code object <listcomp> at 0x1624c5b3790, file <string>>, line 265)
             194 LOAD_CONST           ("IIiI1i.<locals>.<listcomp>")
             196 MAKE_FUNCTION        (No arguments)
             198 LOAD_FAST            (OoOOooO0oOO0Oo)
             200 GET_ITER
             202 CALL_FUNCTION        (1 positional argument)
             204 CALL_METHOD          (1 positional argument)
             206 STORE_FAST           (ii1IiiIiI)

266:         208 LOAD_GLOBAL          (datetime)
             210 LOAD_ATTR            (timedelta)
             212 LOAD_CONST           (3)
             214 LOAD_CONST           (('days',))
             216 CALL_FUNCTION_KW     (1 total positional and keyword args)
             218 STORE_FAST           (Ooo0O00o)

267:         220 LOAD_GLOBAL          (CACHE)
             222 LOAD_ATTR            (set)
             224 LOAD_DEREF           (p3Item)
             226 LOAD_ATTR            (nameWidget)
             228 LOAD_FAST            (OoOOooO0oOO0Oo)
             230 LOAD_CONST           (True)
             232 LOAD_DEREF           (p3Item)
             234 LOAD_ATTR            (content)
             236 LOAD_FAST            (Ooo0O00o)

268:         238 LOAD_FAST            (ii1IiiIiI)

267:         240 LOAD_CONST           (('pickle_data', 'sub_categoria', 'expiration', 'inWidget'))
             242 CALL_FUNCTION_KW     (6 total positional and keyword args)
             244 POP_TOP

270:     >>  246 LOAD_FAST            (OoOOooO0oOO0Oo)
             248 EXTENDED_ARG         (512)
             250 POP_JUMP_IF_FALSE    (to 752)

272:         252 LOAD_FAST            (OoOOooO0oOO0Oo)
             254 LOAD_CONST           ("<listcomp>")
             256 BINARY_SUBSCR
             258 LOAD_ATTR            (content)
             260 STORE_FAST           (O0ooOO0O0O0O)

273:         262 LOAD_GLOBAL          (Watched)
             264 CALL_FUNCTION        (0 positional arguments)
             266 SETUP_WITH           (to 284)
             268 STORE_FAST           (I11I1iI)

274:         270 LOAD_FAST            (I11I1iI)
             272 LOAD_METHOD          (getView)
             274 LOAD_FAST            (O0ooOO0O0O0O)
             276 CALL_METHOD          (1 positional argument)
             278 STORE_FAST           (OOOoo)

275:         280 POP_BLOCK
             282 BEGIN_FINALLY
         >>  284 WITH_CLEANUP_START
             286 WITH_CLEANUP_FINISH
             288 END_FINALLY

276:         290 LOAD_CONST           ("")
             292 STORE_FAST           (Ii1Ii1)

277:         294 LOAD_FAST            (OoOOooO0oOO0Oo)
             296 GET_ITER
         >>  298 FOR_ITER             (to 536)
             300 STORE_FAST           (I111i1i11iII)

278:         302 LOAD_FAST            (I111i1i11iII)
             304 LOAD_METHOD          (is_label)
             306 CALL_METHOD          (0 positional arguments)
             308 EXTENDED_ARG         (256)
             310 POP_JUMP_IF_FALSE    (to 332)
             312 LOAD_FAST            (OOOoo)
             314 LOAD_CONST           ((50, 51, 55))
             316 COMPARE_OP           (not-in)
             318 EXTENDED_ARG         (256)
             320 POP_JUMP_IF_FALSE    (to 332)

280:         322 LOAD_FAST            (I111i1i11iII)
             324 LOAD_ATTR            (label)
             326 STORE_FAST           (Ii1Ii1)

281:         328 EXTENDED_ARG         (256)
             330 JUMP_ABSOLUTE        (to 298)

283:     >>  332 LOAD_FAST            (Ii1Ii1)
             334 EXTENDED_ARG         (256)
             336 POP_JUMP_IF_FALSE    (to 414)

284:         338 SETUP_FINALLY        (to 398)

285:         340 LOAD_GLOBAL          (re)
             342 LOAD_METHOD          (findall)
             344 LOAD_CONST           ("]([^\\[]+)")
             346 LOAD_FAST            (I111i1i11iII)
             348 LOAD_ATTR            (label)
             350 CALL_METHOD          (2 positional arguments)
             352 LOAD_CONST           ("<listcomp>")
             354 BINARY_SUBSCR
             356 LOAD_METHOD          (startswith)
             358 LOAD_CONST           (" ")
             360 CALL_METHOD          (1 positional argument)
             362 EXTENDED_ARG         (256)
             364 POP_JUMP_IF_FALSE    (to 390)

286:         366 LOAD_GLOBAL          (re)
             368 LOAD_METHOD          (sub)
             370 LOAD_CONST           ("\\\\n|\\\\r|\\\\t|\\\\s{2}|&nbsp;")
             372 LOAD_CONST           ("")
             374 LOAD_FAST            (Ii1Ii1)
             376 LOAD_FAST            (I111i1i11iII)
             378 LOAD_ATTR            (label)
             380 BINARY_ADD
             382 CALL_METHOD          (3 positional arguments)
             384 LOAD_FAST            (I111i1i11iII)
             386 STORE_ATTR           (label)
             388 JUMP_FORWARD         (to 394)

288:     >>  390 LOAD_CONST           ("")
             392 STORE_FAST           (Ii1Ii1)
         >>  394 POP_BLOCK
             396 JUMP_FORWARD         (to 414)

289:     >>  398 POP_TOP
             400 POP_TOP
             402 POP_TOP

290:         404 LOAD_CONST           ("")
             406 STORE_FAST           (Ii1Ii1)

291:         408 POP_EXCEPT
             410 JUMP_FORWARD         (to 414)
             412 END_FINALLY

292:     >>  414 LOAD_GLOBAL          (xbmcgui)
             416 LOAD_METHOD          (ListItem)
             418 LOAD_FAST            (I111i1i11iII)
             420 LOAD_ATTR            (label)
             422 EXTENDED_ARG         (256)
             424 JUMP_IF_TRUE_OR_POP  (to 430)
             426 LOAD_FAST            (I111i1i11iII)
             428 LOAD_ATTR            (title)
         >>  430 CALL_METHOD          (1 positional argument)
             432 STORE_FAST           (i11I1IiIiI1i)

294:         434 LOAD_FAST            (I111i1i11iII)
             436 LOAD_ATTR            (isPlayable)
             438 EXTENDED_ARG         (256)
             440 POP_JUMP_IF_FALSE    (to 448)

295:         442 LOAD_CONST           (False)
             444 STORE_FAST           (ii11I1i1i)
             446 JUMP_FORWARD         (to 488)

296:     >>  448 LOAD_GLOBAL          (isinstance)
             450 LOAD_FAST            (I111i1i11iII)
             452 LOAD_ATTR            (isFolder)
             454 LOAD_GLOBAL          (bool)
             456 CALL_FUNCTION        (2 positional arguments)
             458 EXTENDED_ARG         (256)
             460 POP_JUMP_IF_FALSE    (to 470)

297:         462 LOAD_FAST            (I111i1i11iII)
             464 LOAD_ATTR            (isFolder)
             466 STORE_FAST           (ii11I1i1i)
             468 JUMP_FORWARD         (to 488)

298:     >>  470 LOAD_FAST            (I111i1i11iII)
             472 LOAD_ATTR            (action)
             474 EXTENDED_ARG         (256)
             476 POP_JUMP_IF_TRUE     (to 484)

299:         478 LOAD_CONST           (False)
             480 STORE_FAST           (ii11I1i1i)
             482 JUMP_FORWARD         (to 488)

301:     >>  484 LOAD_CONST           (True)
             486 STORE_FAST           (ii11I1i1i)

303:     >>  488 LOAD_GLOBAL          (setInfoTag)
             490 LOAD_FAST            (i11I1IiIiI1i)
             492 LOAD_FAST            (I111i1i11iII)
             494 CALL_FUNCTION        (2 positional arguments)
             496 POP_TOP

304:         498 LOAD_FAST            (iiI1i1IiiiIi1)
             500 LOAD_METHOD          (append)
             502 LOAD_CONST           ("%s?%s")
             504 LOAD_GLOBAL          (sys)
             506 LOAD_ATTR            (argv)
             508 LOAD_CONST           ("<listcomp>")
             510 BINARY_SUBSCR
             512 LOAD_FAST            (I111i1i11iII)
             514 LOAD_METHOD          (tourl)
             516 CALL_METHOD          (0 positional arguments)
             518 BUILD_TUPLE          2
             520 BINARY_MODULO

305:         522 LOAD_FAST            (i11I1IiIiI1i)

306:         524 LOAD_FAST            (ii11I1i1i)

304:         526 BUILD_TUPLE          3
             528 CALL_METHOD          (1 positional argument)
             530 POP_TOP

307:         532 EXTENDED_ARG         (256)
             534 JUMP_ABSOLUTE        (to 298)

308:     >>  536 LOAD_FAST            (iiI1i1IiiiIi1)
             538 EXTENDED_ARG         (512)
             540 POP_JUMP_IF_FALSE    (to 648)

309:         542 LOAD_GLOBAL          (xbmcplugin)
             544 LOAD_METHOD          (addDirectoryItems)
             546 LOAD_GLOBAL          (int)
             548 LOAD_GLOBAL          (sys)
             550 LOAD_ATTR            (argv)
             552 LOAD_CONST           (1)
             554 BINARY_SUBSCR
             556 CALL_FUNCTION        (1 positional argument)
             558 LOAD_FAST            (iiI1i1IiiiIi1)
             560 LOAD_GLOBAL          (len)
             562 LOAD_FAST            (iiI1i1IiiiIi1)
             564 CALL_FUNCTION        (1 positional argument)
             566 CALL_METHOD          (3 positional arguments)
             568 POP_TOP

311:         570 LOAD_DEREF           (p3Item)
             572 LOAD_ATTR            (label)
             574 EXTENDED_ARG         (512)
             576 POP_JUMP_IF_FALSE    (to 618)

312:         578 LOAD_GLOBAL          (re)
             580 LOAD_METHOD          (sub)
             582 LOAD_CONST           ("\\[[^\\]]*]")
             584 LOAD_CONST           ("")
             586 LOAD_DEREF           (p3Item)
             588 LOAD_ATTR            (label)
             590 CALL_METHOD          (3 positional arguments)
             592 STORE_FAST           (o0OOo0OoO)

313:         594 LOAD_CONST           ("[COLOR Ffd414fc]Palantir 3[/COLOR] - ")
             596 LOAD_GLOBAL          (re)
             598 LOAD_METHOD          (sub)
             600 LOAD_CONST           ("\\s+")
             602 LOAD_CONST           (" ")
             604 LOAD_FAST            (o0OOo0OoO)
             606 CALL_METHOD          (3 positional arguments)
             608 LOAD_METHOD          (strip)
             610 CALL_METHOD          (0 positional arguments)
             612 BINARY_ADD
             614 STORE_FAST           (o0OOo0OoO)
             616 JUMP_FORWARD         (to 622)

315:     >>  618 LOAD_CONST           ("[COLOR Ffd414fc]Palantir 3[/COLOR]")
             620 STORE_FAST           (o0OOo0OoO)

316:     >>  622 LOAD_GLOBAL          (xbmcplugin)
             624 LOAD_ATTR            (setProperty)
             626 LOAD_GLOBAL          (int)
             628 LOAD_GLOBAL          (sys)
             630 LOAD_ATTR            (argv)
             632 LOAD_CONST           (1)
             634 BINARY_SUBSCR
             636 CALL_FUNCTION        (1 positional argument)
             638 LOAD_CONST           ("breadcrumbs_label")
             640 LOAD_FAST            (o0OOo0OoO)
             642 LOAD_CONST           (('handle', 'key', 'value'))
             644 CALL_FUNCTION_KW     (3 total positional and keyword args)
             646 POP_TOP

318:     >>  648 LOAD_GLOBAL          (xbmcplugin)
             650 LOAD_ATTR            (addSortMethod)
             652 LOAD_GLOBAL          (int)
             654 LOAD_GLOBAL          (sys)
             656 LOAD_ATTR            (argv)
             658 LOAD_CONST           (1)
             660 BINARY_SUBSCR
             662 CALL_FUNCTION        (1 positional argument)
             664 LOAD_GLOBAL          (xbmcplugin)
             666 LOAD_ATTR            (SORT_METHOD_NONE)
             668 LOAD_CONST           (('handle', 'sortMethod'))
             670 CALL_FUNCTION_KW     (2 total positional and keyword args)
             672 POP_TOP

319:         674 LOAD_GLOBAL          (xbmcplugin)
             676 LOAD_METHOD          (setContent)
             678 LOAD_GLOBAL          (int)
             680 LOAD_GLOBAL          (sys)
             682 LOAD_ATTR            (argv)
             684 LOAD_CONST           (1)
             686 BINARY_SUBSCR
             688 CALL_FUNCTION        (1 positional argument)
             690 LOAD_FAST            (O0ooOO0O0O0O)
             692 CALL_METHOD          (2 positional arguments)
             694 POP_TOP

320:         696 LOAD_GLOBAL          (xbmcplugin)
             698 LOAD_ATTR            (endOfDirectory)
             700 LOAD_GLOBAL          (int)
             702 LOAD_GLOBAL          (sys)
             704 LOAD_ATTR            (argv)
             706 LOAD_CONST           (1)
             708 BINARY_SUBSCR
             710 CALL_FUNCTION        (1 positional argument)
             712 LOAD_CONST           (True)
             714 LOAD_FAST            (Oo0o0Oo)
             716 LOAD_CONST           (('handle', 'succeeded', 'cacheToDisc'))
             718 CALL_FUNCTION_KW     (3 total positional and keyword args)
             720 POP_TOP

321:         722 LOAD_GLOBAL          (ISESTUARYPALANTIR)
             724 EXTENDED_ARG         (512)
             726 POP_JUMP_IF_TRUE     (to 752)

322:         728 LOAD_GLOBAL          (xbmc)
             730 LOAD_METHOD          (sleep)
             732 LOAD_CONST           (100)
             734 CALL_METHOD          (1 positional argument)
             736 POP_TOP

323:         738 LOAD_GLOBAL          (xbmc)
             740 LOAD_METHOD          (executebuiltin)
             742 LOAD_CONST           ("Container.SetViewMode(%s)")
             744 LOAD_FAST            (OOOoo)
             746 BINARY_MODULO
             748 CALL_METHOD          (1 positional argument)
             750 POP_TOP

325:     >>  752 LOAD_CONST           (None)
             754 RETURN_VALUE


# Method Name:       iii1i1iiIi1
# Filename:          <string>
# Argument count:    0
# Position-only argument count: 0
# Keyword-only arguments: 0
# Number of locals:  1
# Stack size:        9
# Flags:             0x00000043 (NOFREE | NEWLOCALS | OPTIMIZED)
# First Line:        326
# Constants:
#    0: None
# Names:
#    0: Watched
#    1: syncToTrakt
#    2: OooOoo
#    3: ooOOO
#    4: I1Ii1I1
#    5: Iii1i
#    6: Ii
# Varnames:
#	I11I1iI
# Local variables:
#    0: I11I1iI

327:           0 LOAD_GLOBAL          (Watched)
               2 CALL_FUNCTION        (0 positional arguments)
               4 SETUP_WITH           (to 20)
               6 STORE_FAST           (I11I1iI)

328:           8 LOAD_FAST            (I11I1iI)
              10 LOAD_METHOD          (syncToTrakt)
              12 CALL_METHOD          (0 positional arguments)
              14 POP_TOP

330:          16 POP_BLOCK
              18 BEGIN_FINALLY
         >>   20 WITH_CLEANUP_START
              22 WITH_CLEANUP_FINISH
              24 END_FINALLY
              26 LOAD_CONST           (None)
              28 RETURN_VALUE


# Method Name:       IiI11Ii111
# Filename:          <string>
# Argument count:    0
# Position-only argument count: 0
# Keyword-only arguments: 0
# Number of locals:  0
# Stack size:        2
# Flags:             0x00000040 (NOFREE)
# First Line:        22
# Constants:
#    0: 'I1i.<locals>.IiI11Ii111'
#    1: <Code38 code object __init__ at 0x1624c515550, file <string>>, line 23
#    2: 'I1i.<locals>.IiI11Ii111.__init__'
#    3: <Code38 code object has_module at 0x1624c515350, file <string>>, line 25
#    4: 'I1i.<locals>.IiI11Ii111.has_module'
#    5: <Code38 code object create_module at 0x1624c514fd0, file <string>>, line 27
#    6: 'I1i.<locals>.IiI11Ii111.create_module'
#    7: <Code38 code object exec_module at 0x1624c514d10, file <string>>, line 32
#    8: 'I1i.<locals>.IiI11Ii111.exec_module'
#    9: None
# Names:
#    0: __name__
#    1: __module__
#    2: __qualname__
#    3: __init__
#    4: has_module
#    5: create_module
#    6: exec_module

 22:           0 LOAD_NAME            (__name__)
               2 STORE_NAME           (__module__)
               4 LOAD_CONST           ("I1i.<locals>.IiI11Ii111")
               6 STORE_NAME           (__qualname__)

 23:           8 LOAD_CONST           (<Code38 code object __init__ at 0x1624c515550, file <string>>, line 23)
              10 LOAD_CONST           ("I1i.<locals>.IiI11Ii111.__init__")
              12 MAKE_FUNCTION        (No arguments)
              14 STORE_NAME           (__init__)

 25:          16 LOAD_CONST           (<Code38 code object has_module at 0x1624c515350, file <string>>, line 25)
              18 LOAD_CONST           ("I1i.<locals>.IiI11Ii111.has_module")
              20 MAKE_FUNCTION        (No arguments)
              22 STORE_NAME           (has_module)

 27:          24 LOAD_CONST           (<Code38 code object create_module at 0x1624c514fd0, file <string>>, line 27)
              26 LOAD_CONST           ("I1i.<locals>.IiI11Ii111.create_module")
              28 MAKE_FUNCTION        (No arguments)
              30 STORE_NAME           (create_module)

 32:          32 LOAD_CONST           (<Code38 code object exec_module at 0x1624c514d10, file <string>>, line 32)
              34 LOAD_CONST           ("I1i.<locals>.IiI11Ii111.exec_module")
              36 MAKE_FUNCTION        (No arguments)
              38 STORE_NAME           (exec_module)
              40 LOAD_CONST           (None)
              42 RETURN_VALUE


# Method Name:       iIi
# Filename:          <string>
# Argument count:    0
# Position-only argument count: 0
# Keyword-only arguments: 0
# Number of locals:  0
# Stack size:        3
# Flags:             0x00000040 (NOFREE)
# First Line:        34
# Constants:
#    0: 'I1i.<locals>.iIi'
#    1: <Code38 code object __init__ at 0x1624c514590, file <string>>, line 35
#    2: 'I1i.<locals>.iIi.__init__'
#    3: None
#    4: <Code38 code object find_spec at 0x1624c514050, file <string>>, line 37
#    5: 'I1i.<locals>.iIi.find_spec'
#    6: (None,)
# Names:
#    0: __name__
#    1: __module__
#    2: __qualname__
#    3: __init__
#    4: find_spec

 34:           0 LOAD_NAME            (__name__)
               2 STORE_NAME           (__module__)
               4 LOAD_CONST           ("I1i.<locals>.iIi")
               6 STORE_NAME           (__qualname__)

 35:           8 LOAD_CONST           (<Code38 code object __init__ at 0x1624c514590, file <string>>, line 35)
              10 LOAD_CONST           ("I1i.<locals>.iIi.__init__")
              12 MAKE_FUNCTION        (No arguments)
              14 STORE_NAME           (__init__)

 37:          16 LOAD_CONST           ((None,))
              18 LOAD_CONST           (<Code38 code object find_spec at 0x1624c514050, file <string>>, line 37)
              20 LOAD_CONST           ("I1i.<locals>.iIi.find_spec")
              22 MAKE_FUNCTION        (default)
              24 STORE_NAME           (find_spec)
              26 LOAD_CONST           (None)
              28 RETURN_VALUE


# Method Name:       <lambda>
# Filename:          <string>
# Argument count:    0
# Position-only argument count: 0
# Keyword-only arguments: 0
# Number of locals:  0
# Stack size:        5
# Flags:             0x00000013 (NESTED | NEWLOCALS | OPTIMIZED)
# First Line:        254
# Constants:
#    0: None
#    1: 'libs.ioiI1iIiiIi'
#    2: 'listado_random'
#    3: ('fromlist',)
# Names:
#    0: getattr
#    1: __import__
# Cell variables:
#    0: p3Item

254:           0 LOAD_GLOBAL          (getattr)
               2 LOAD_GLOBAL          (__import__)
               4 LOAD_CONST           ("libs.ioiI1iIiiIi")
               6 LOAD_CONST           ("listado_random")
               8 BUILD_LIST           1
              10 LOAD_CONST           (('fromlist',))
              12 CALL_FUNCTION_KW     (2 total positional and keyword args)
              14 LOAD_CONST           ("listado_random")
              16 CALL_FUNCTION        (2 positional arguments)
              18 LOAD_DEREF           (p3Item)
              20 CALL_FUNCTION        (1 positional argument)
              22 RETURN_VALUE


# Method Name:       <listcomp>
# Filename:          <string>
# Argument count:    1
# Position-only argument count: 0
# Keyword-only arguments: 0
# Number of locals:  2
# Stack size:        3
# Flags:             0x00000053 (NOFREE | NESTED | NEWLOCALS | OPTIMIZED)
# First Line:        265
# Names:
#    0: tmdb
# Varnames:
#	.0, it
# Positional arguments:
#	.0
# Local variables:
#    1: it

265:           0 BUILD_LIST           0
               2 LOAD_FAST            (.0)
         >>    4 FOR_ITER             (to 22)

265:           6 STORE_FAST           (it)

265:           8 LOAD_FAST            (it)
              10 LOAD_ATTR            (tmdb)
              12 POP_JUMP_IF_FALSE    (to 4)

265:          14 LOAD_FAST            (it)
              16 LOAD_ATTR            (tmdb)
              18 LIST_APPEND          2
              20 JUMP_ABSOLUTE        (to 4)
         >>   22 RETURN_VALUE


# Method Name:       __init__
# Filename:          <string>
# Argument count:    2
# Position-only argument count: 0
# Keyword-only arguments: 0
# Number of locals:  2
# Stack size:        2
# Flags:             0x00000053 (NOFREE | NESTED | NEWLOCALS | OPTIMIZED)
# First Line:        23
# Constants:
#    0: None
# Names:
#    0: _modules
# Varnames:
#	self, modules
# Positional arguments:
#	self, modules

 24:           0 LOAD_FAST            (modules)
               2 LOAD_FAST            (self)
               4 STORE_ATTR           (_modules)
               6 LOAD_CONST           (None)
               8 RETURN_VALUE


# Method Name:       has_module
# Filename:          <string>
# Argument count:    2
# Position-only argument count: 0
# Keyword-only arguments: 0
# Number of locals:  2
# Stack size:        2
# Flags:             0x00000053 (NOFREE | NESTED | NEWLOCALS | OPTIMIZED)
# First Line:        25
# Constants:
#    0: None
# Names:
#    0: _modules
# Varnames:
#	self, fullname
# Positional arguments:
#	self, fullname

 26:           0 LOAD_FAST            (fullname)
               2 LOAD_FAST            (self)
               4 LOAD_ATTR            (_modules)
               6 COMPARE_OP           (in)
               8 RETURN_VALUE


# Method Name:       create_module
# Filename:          <string>
# Argument count:    2
# Position-only argument count: 0
# Keyword-only arguments: 0
# Number of locals:  3
# Stack size:        3
# Flags:             0x00000053 (NOFREE | NESTED | NEWLOCALS | OPTIMIZED)
# First Line:        27
# Constants:
#    0: None
# Names:
#    0: has_module
#    1: name
#    2: ModuleType
#    3: exec
#    4: _modules
#    5: __dict__
# Varnames:
#	self, spec, I11II1Ii
# Positional arguments:
#	self, spec
# Local variables:
#    2: I11II1Ii

 28:           0 LOAD_FAST            (self)
               2 LOAD_METHOD          (has_module)
               4 LOAD_FAST            (spec)
               6 LOAD_ATTR            (name)
               8 CALL_METHOD          (1 positional argument)
              10 POP_JUMP_IF_FALSE    (to 46)

 29:          12 LOAD_GLOBAL          (ModuleType)
              14 LOAD_FAST            (spec)
              16 LOAD_ATTR            (name)
              18 CALL_FUNCTION        (1 positional argument)
              20 STORE_FAST           (I11II1Ii)

 30:          22 LOAD_GLOBAL          (exec)
              24 LOAD_FAST            (self)
              26 LOAD_ATTR            (_modules)
              28 LOAD_FAST            (spec)
              30 LOAD_ATTR            (name)
              32 BINARY_SUBSCR
              34 LOAD_FAST            (I11II1Ii)
              36 LOAD_ATTR            (__dict__)
              38 CALL_FUNCTION        (2 positional arguments)
              40 POP_TOP

 31:          42 LOAD_FAST            (I11II1Ii)
              44 RETURN_VALUE
         >>   46 LOAD_CONST           (None)
              48 RETURN_VALUE


# Method Name:       exec_module
# Filename:          <string>
# Argument count:    2
# Position-only argument count: 0
# Keyword-only arguments: 0
# Number of locals:  2
# Stack size:        1
# Flags:             0x00000053 (NOFREE | NESTED | NEWLOCALS | OPTIMIZED)
# First Line:        32
# Constants:
#    0: None
# Varnames:
#	self, module
# Positional arguments:
#	self, module

 33:           0 LOAD_CONST           (None)
               2 RETURN_VALUE


# Method Name:       __init__
# Filename:          <string>
# Argument count:    2
# Position-only argument count: 0
# Keyword-only arguments: 0
# Number of locals:  2
# Stack size:        2
# Flags:             0x00000053 (NOFREE | NESTED | NEWLOCALS | OPTIMIZED)
# First Line:        35
# Constants:
#    0: None
# Names:
#    0: _loader
# Varnames:
#	self, loader
# Positional arguments:
#	self, loader

 36:           0 LOAD_FAST            (loader)
               2 LOAD_FAST            (self)
               4 STORE_ATTR           (_loader)
               6 LOAD_CONST           (None)
               8 RETURN_VALUE


# Method Name:       find_spec
# Filename:          <string>
# Argument count:    4
# Position-only argument count: 0
# Keyword-only arguments: 0
# Number of locals:  4
# Stack size:        4
# Flags:             0x00000053 (NOFREE | NESTED | NEWLOCALS | OPTIMIZED)
# First Line:        37
# Constants:
#    0: None
# Names:
#    0: _loader
#    1: has_module
#    2: machinery
#    3: ModuleSpec
# Varnames:
#	self, fullname, path, target
# Positional arguments:
#	self, fullname, path, target

 38:           0 LOAD_FAST            (self)
               2 LOAD_ATTR            (_loader)
               4 LOAD_METHOD          (has_module)
               6 LOAD_FAST            (fullname)
               8 CALL_METHOD          (1 positional argument)
              10 POP_JUMP_IF_FALSE    (to 26)

 39:          12 LOAD_GLOBAL          (machinery)
              14 LOAD_METHOD          (ModuleSpec)
              16 LOAD_FAST            (fullname)
              18 LOAD_FAST            (self)
              20 LOAD_ATTR            (_loader)
              22 CALL_METHOD          (2 positional arguments)
              24 RETURN_VALUE
         >>   26 LOAD_CONST           (None)
              28 RETURN_VALUE


CHILD CODE OBJECTS:

